// class version 61.0 (61)
// access flags 0x21
public class org/mpisws/concurrent/programs/simple/counter/Counter {

  // compiled from: Counter.java

  // access flags 0x2
  private I count

  // access flags 0x1
  public <init>()V
   L0
    LINENUMBER 3 L0
    ALOAD 0
    INVOKESPECIAL java/lang/Object.<init> ()V
   L1
    LINENUMBER 4 L1
    ALOAD 0
    ICONST_0
    DUP2
    INVOKESTATIC java/lang/Integer.valueOf (I)Ljava/lang/Integer;
    INVOKESTATIC java/lang/Thread.currentThread ()Ljava/lang/Thread;
    LDC "org.mpisws.concurrent.programs.simple.counter.Counter"
    LDC "count"
    LDC "I"
    INVOKESTATIC org/mpisws/runtime/RuntimeEnvironment.writeOperation (Ljava/lang/Object;Ljava/lang/Object;Ljava/lang/Thread;Ljava/lang/String;Ljava/lang/String;Ljava/lang/String;)V
    PUTFIELD org/mpisws/concurrent/programs/simple/counter/Counter.count : I
    INVOKESTATIC java/lang/Thread.currentThread ()Ljava/lang/Thread;
    INVOKESTATIC org/mpisws/runtime/RuntimeEnvironment.waitRequest (Ljava/lang/Thread;)V
    NOP
    RETURN
    MAXSTACK = 8
    MAXLOCALS = 1

  // access flags 0x1
  public getValue()I
   L0
    LINENUMBER 7 L0
    ALOAD 0
    DUP
    INVOKESTATIC java/lang/Thread.currentThread ()Ljava/lang/Thread;
    LDC "org.mpisws.concurrent.programs.simple.counter.Counter"
    LDC "count"
    LDC "I"
    INVOKESTATIC org/mpisws/runtime/RuntimeEnvironment.readOperation (Ljava/lang/Object;Ljava/lang/Thread;Ljava/lang/String;Ljava/lang/String;Ljava/lang/String;)V
    GETFIELD org/mpisws/concurrent/programs/simple/counter/Counter.count : I
    INVOKESTATIC java/lang/Thread.currentThread ()Ljava/lang/Thread;
    INVOKESTATIC org/mpisws/runtime/RuntimeEnvironment.waitRequest (Ljava/lang/Thread;)V
    NOP
    IRETURN
    MAXSTACK = 6
    MAXLOCALS = 1

  // access flags 0x1
  public increment()V
   L0
    LINENUMBER 11 L0
    ALOAD 0
    DUP
    DUP
    INVOKESTATIC java/lang/Thread.currentThread ()Ljava/lang/Thread;
    LDC "org.mpisws.concurrent.programs.simple.counter.Counter"
    LDC "count"
    LDC "I"
    INVOKESTATIC org/mpisws/runtime/RuntimeEnvironment.readOperation (Ljava/lang/Object;Ljava/lang/Thread;Ljava/lang/String;Ljava/lang/String;Ljava/lang/String;)V
    GETFIELD org/mpisws/concurrent/programs/simple/counter/Counter.count : I
    INVOKESTATIC java/lang/Thread.currentThread ()Ljava/lang/Thread;
    INVOKESTATIC org/mpisws/runtime/RuntimeEnvironment.waitRequest (Ljava/lang/Thread;)V
    NOP
    ICONST_1
    IADD
    DUP2
    INVOKESTATIC java/lang/Integer.valueOf (I)Ljava/lang/Integer;
    INVOKESTATIC java/lang/Thread.currentThread ()Ljava/lang/Thread;
    LDC "org.mpisws.concurrent.programs.simple.counter.Counter"
    LDC "count"
    LDC "I"
    INVOKESTATIC org/mpisws/runtime/RuntimeEnvironment.writeOperation (Ljava/lang/Object;Ljava/lang/Object;Ljava/lang/Thread;Ljava/lang/String;Ljava/lang/String;Ljava/lang/String;)V
    PUTFIELD org/mpisws/concurrent/programs/simple/counter/Counter.count : I
    INVOKESTATIC java/lang/Thread.currentThread ()Ljava/lang/Thread;
    INVOKESTATIC org/mpisws/runtime/RuntimeEnvironment.waitRequest (Ljava/lang/Thread;)V
    NOP
   L1
    LINENUMBER 12 L1
    RETURN
    MAXSTACK = 8
    MAXLOCALS = 1
}
