// class version 61.0 (61)
// access flags 0x21
public class org/mpisws/concurrent/programs/symbolic/counter/Counter {

  // compiled from: Counter.java
  // access flags 0x19
  public final static INNERCLASS java/lang/invoke/MethodHandles$Lookup java/lang/invoke/MethodHandles Lookup

  // access flags 0x12
  private final Lorg/mpisws/symbolic/SymbolicInteger; x

  // access flags 0x2
  private I count

  // access flags 0x1
  public <init>(Lorg/mpisws/symbolic/SymbolicInteger;)V
   L0
    LINENUMBER 11 L0
    ALOAD 0
    INVOKESPECIAL java/lang/Object.<init> ()V
   L1
    LINENUMBER 9 L1
    ALOAD 0
    ICONST_0
    DUP2
    INVOKESTATIC java/lang/Integer.valueOf (I)Ljava/lang/Integer;
    INVOKESTATIC java/lang/Thread.currentThread ()Ljava/lang/Thread;
    LDC "org.mpisws.concurrent.programs.symbolic.counter.Counter"
    LDC "count"
    LDC "I"
    INVOKESTATIC org/mpisws/runtime/RuntimeEnvironment.writeOperation (Ljava/lang/Object;Ljava/lang/Object;Ljava/lang/Thread;Ljava/lang/String;Ljava/lang/String;Ljava/lang/String;)V
    PUTFIELD org/mpisws/concurrent/programs/symbolic/counter/Counter.count : I
    INVOKESTATIC java/lang/Thread.currentThread ()Ljava/lang/Thread;
    INVOKESTATIC org/mpisws/runtime/RuntimeEnvironment.waitRequest (Ljava/lang/Thread;)V
    NOP
   L2
    LINENUMBER 12 L2
    ALOAD 0
    ALOAD 1
    PUTFIELD org/mpisws/concurrent/programs/symbolic/counter/Counter.x : Lorg/mpisws/symbolic/SymbolicInteger;
   L3
    LINENUMBER 13 L3
    RETURN
    MAXSTACK = 8
    MAXLOCALS = 2

  // access flags 0x1
  public inc()V
   L0
    LINENUMBER 16 L0
    NEW org/mpisws/symbolic/ArithmeticStatement
    DUP
    INVOKESPECIAL org/mpisws/symbolic/ArithmeticStatement.<init> ()V
    ASTORE 1
   L1
    LINENUMBER 17 L1
    GETSTATIC java/lang/System.out : Ljava/io/PrintStream;
    INVOKESTATIC java/lang/Thread.currentThread ()Ljava/lang/Thread;
    INVOKEVIRTUAL java/lang/Thread.getId ()J
    ALOAD 1
    INVOKEDYNAMIC makeConcatWithConstants(JLorg/mpisws/symbolic/ArithmeticStatement;)Ljava/lang/String; [
      // handle kind 0x6 : INVOKESTATIC
      java/lang/invoke/StringConcatFactory.makeConcatWithConstants(Ljava/lang/invoke/MethodHandles$Lookup;Ljava/lang/String;Ljava/lang/invoke/MethodType;Ljava/lang/String;[Ljava/lang/Object;)Ljava/lang/invoke/CallSite;
      // arguments:
      "[Thread Message] : Thread-\u0001 the stmt is: \u0001"
    ]
    INVOKEVIRTUAL java/io/PrintStream.println (Ljava/lang/String;)V
   L2
    LINENUMBER 18 L2
    ALOAD 1
    ALOAD 0
    GETFIELD org/mpisws/concurrent/programs/symbolic/counter/Counter.x : Lorg/mpisws/symbolic/SymbolicInteger;
    ICONST_1
    INVOKEVIRTUAL org/mpisws/symbolic/ArithmeticStatement.add (Lorg/mpisws/symbolic/AbstractInteger;I)V
   L3
    LINENUMBER 19 L3
    ALOAD 0
    GETFIELD org/mpisws/concurrent/programs/symbolic/counter/Counter.x : Lorg/mpisws/symbolic/SymbolicInteger;
    ALOAD 1
    INVOKEVIRTUAL org/mpisws/symbolic/SymbolicInteger.assign (Lorg/mpisws/symbolic/ArithmeticStatement;)V
   L4
    LINENUMBER 20 L4
    NEW org/mpisws/symbolic/ArithmeticFormula
    DUP
    INVOKESPECIAL org/mpisws/symbolic/ArithmeticFormula.<init> ()V
    ASTORE 2
   L5
    LINENUMBER 21 L5
    ALOAD 2
    ALOAD 0
    GETFIELD org/mpisws/concurrent/programs/symbolic/counter/Counter.x : Lorg/mpisws/symbolic/SymbolicInteger;
    BIPUSH 10
    INVOKEVIRTUAL org/mpisws/symbolic/ArithmeticFormula.gt (Lorg/mpisws/symbolic/AbstractInteger;I)Lorg/mpisws/symbolic/SymbolicOperation;
    ASTORE 3
   L6
    LINENUMBER 22 L6
    NEW org/mpisws/symbolic/SymbolicFormula
    DUP
    INVOKESPECIAL org/mpisws/symbolic/SymbolicFormula.<init> ()V
    ASTORE 4
   L7
    LINENUMBER 23 L7
    ALOAD 4
    ALOAD 3
    INVOKEVIRTUAL org/mpisws/symbolic/SymbolicFormula.evaluate (Lorg/mpisws/symbolic/SymbolicOperation;)Z
    INVOKESTATIC java/lang/Thread.currentThread ()Ljava/lang/Thread;
    INVOKESTATIC org/mpisws/runtime/RuntimeEnvironment.waitRequest (Ljava/lang/Thread;)V
    NOP
    IFEQ L8
   L9
    LINENUMBER 24 L9
    ALOAD 0
    DUP
    DUP
    INVOKESTATIC java/lang/Thread.currentThread ()Ljava/lang/Thread;
    LDC "org.mpisws.concurrent.programs.symbolic.counter.Counter"
    LDC "count"
    LDC "I"
    INVOKESTATIC org/mpisws/runtime/RuntimeEnvironment.readOperation (Ljava/lang/Object;Ljava/lang/Thread;Ljava/lang/String;Ljava/lang/String;Ljava/lang/String;)V
    GETFIELD org/mpisws/concurrent/programs/symbolic/counter/Counter.count : I
    INVOKESTATIC java/lang/Thread.currentThread ()Ljava/lang/Thread;
    INVOKESTATIC org/mpisws/runtime/RuntimeEnvironment.waitRequest (Ljava/lang/Thread;)V
    NOP
    ICONST_1
    IADD
    DUP2
    INVOKESTATIC java/lang/Integer.valueOf (I)Ljava/lang/Integer;
    INVOKESTATIC java/lang/Thread.currentThread ()Ljava/lang/Thread;
    LDC "org.mpisws.concurrent.programs.symbolic.counter.Counter"
    LDC "count"
    LDC "I"
    INVOKESTATIC org/mpisws/runtime/RuntimeEnvironment.writeOperation (Ljava/lang/Object;Ljava/lang/Object;Ljava/lang/Thread;Ljava/lang/String;Ljava/lang/String;Ljava/lang/String;)V
    PUTFIELD org/mpisws/concurrent/programs/symbolic/counter/Counter.count : I
    INVOKESTATIC java/lang/Thread.currentThread ()Ljava/lang/Thread;
    INVOKESTATIC org/mpisws/runtime/RuntimeEnvironment.waitRequest (Ljava/lang/Thread;)V
    NOP
   L8
    LINENUMBER 26 L8
   FRAME FULL [org/mpisws/concurrent/programs/symbolic/counter/Counter org/mpisws/symbolic/ArithmeticStatement org/mpisws/symbolic/ArithmeticFormula org/mpisws/symbolic/SymbolicOperation org/mpisws/symbolic/SymbolicFormula] []
    RETURN
    MAXSTACK = 8
    MAXLOCALS = 5

  // access flags 0x1
  public getCount()I
   L0
    LINENUMBER 29 L0
    ALOAD 0
    DUP
    INVOKESTATIC java/lang/Thread.currentThread ()Ljava/lang/Thread;
    LDC "org.mpisws.concurrent.programs.symbolic.counter.Counter"
    LDC "count"
    LDC "I"
    INVOKESTATIC org/mpisws/runtime/RuntimeEnvironment.readOperation (Ljava/lang/Object;Ljava/lang/Thread;Ljava/lang/String;Ljava/lang/String;Ljava/lang/String;)V
    GETFIELD org/mpisws/concurrent/programs/symbolic/counter/Counter.count : I
    INVOKESTATIC java/lang/Thread.currentThread ()Ljava/lang/Thread;
    INVOKESTATIC org/mpisws/runtime/RuntimeEnvironment.waitRequest (Ljava/lang/Thread;)V
    NOP
    IRETURN
    MAXSTACK = 6
    MAXLOCALS = 1
}
