// class version 61.0 (61)
// access flags 0x21
public class org/mpisws/concurrent/programs/symbolic/counter/SymbolicCounter extends java/lang/Thread {

  // compiled from: SymbolicCounter.java
  // access flags 0x19
  public final static INNERCLASS java/lang/invoke/MethodHandles$Lookup java/lang/invoke/MethodHandles Lookup

  // access flags 0x0
  Lorg/mpisws/concurrent/programs/symbolic/counter/Counter; counter

  // access flags 0x1018
  final static synthetic Z $assertionsDisabled

  // access flags 0x1
  public <init>(Lorg/mpisws/concurrent/programs/symbolic/counter/Counter;)V
   L0
    LINENUMBER 9 L0
    ALOAD 0
    INVOKESPECIAL java/lang/Thread.<init> ()V
   L1
    LINENUMBER 10 L1
    ALOAD 0
    ALOAD 1
    PUTFIELD org/mpisws/concurrent/programs/symbolic/counter/SymbolicCounter.counter : Lorg/mpisws/concurrent/programs/symbolic/counter/Counter;
   L2
    LINENUMBER 11 L2
    RETURN
    MAXSTACK = 2
    MAXLOCALS = 2

  // access flags 0x1
  public run()V
    INVOKESTATIC java/lang/Thread.currentThread ()Ljava/lang/Thread;
    INVOKESTATIC org/mpisws/runtime/RuntimeEnvironment.waitRequest (Ljava/lang/Thread;)V
   L0
    LINENUMBER 15 L0
    ALOAD 0
    GETFIELD org/mpisws/concurrent/programs/symbolic/counter/SymbolicCounter.counter : Lorg/mpisws/concurrent/programs/symbolic/counter/Counter;
    INVOKEVIRTUAL org/mpisws/concurrent/programs/symbolic/counter/Counter.inc ()V
   L1
    LINENUMBER 16 L1
    INVOKESTATIC java/lang/Thread.currentThread ()Ljava/lang/Thread;
    INVOKESTATIC org/mpisws/runtime/RuntimeEnvironment.finishThreadRequest (Ljava/lang/Thread;)V
    RETURN
    MAXSTACK = 1
    MAXLOCALS = 1

  // access flags 0x9
  public static main([Ljava/lang/String;)V throws java/lang/InterruptedException
    INVOKESTATIC java/lang/Thread.currentThread ()Ljava/lang/Thread;
    INVOKESTATIC org/mpisws/runtime/RuntimeEnvironment.init (Ljava/lang/Thread;)V
    NEW org/mpisws/runtime/SchedulerThread
    DUP
    INVOKESPECIAL org/mpisws/runtime/SchedulerThread.<init> ()V
    ASTORE 5
    ALOAD 5
    LDC "SchedulerThread"
    INVOKEVIRTUAL org/mpisws/runtime/SchedulerThread.setName (Ljava/lang/String;)V
    INVOKESTATIC java/lang/Thread.currentThread ()Ljava/lang/Thread;
    ALOAD 5
    INVOKESTATIC org/mpisws/runtime/RuntimeEnvironment.initSchedulerThread (Ljava/lang/Thread;Ljava/lang/Thread;)V
   L0
    LINENUMBER 19 L0
    NEW org/mpisws/symbolic/SymbolicInteger
    DUP
    LDC "x"
    ICONST_1
    INVOKESPECIAL org/mpisws/symbolic/SymbolicInteger.<init> (Ljava/lang/String;Z)V
    ASTORE 1
   L1
    LINENUMBER 20 L1
    NEW org/mpisws/concurrent/programs/symbolic/counter/Counter
    DUP
    ALOAD 1
    INVOKESPECIAL org/mpisws/concurrent/programs/symbolic/counter/Counter.<init> (Lorg/mpisws/symbolic/SymbolicInteger;)V
    ASTORE 2
   L2
    LINENUMBER 21 L2
    NEW org/mpisws/concurrent/programs/symbolic/counter/SymbolicCounter
    DUP
    DUP
    ALOAD 2
    INVOKESPECIAL org/mpisws/concurrent/programs/symbolic/counter/SymbolicCounter.<init> (Lorg/mpisws/concurrent/programs/symbolic/counter/Counter;)V
    INVOKESTATIC org/mpisws/runtime/RuntimeEnvironment.addThread (Ljava/lang/Thread;)V
    ASTORE 3
   L3
    LINENUMBER 22 L3
    NEW org/mpisws/concurrent/programs/symbolic/counter/SymbolicCounter
    DUP
    DUP
    ALOAD 2
    INVOKESPECIAL org/mpisws/concurrent/programs/symbolic/counter/SymbolicCounter.<init> (Lorg/mpisws/concurrent/programs/symbolic/counter/Counter;)V
    INVOKESTATIC org/mpisws/runtime/RuntimeEnvironment.addThread (Ljava/lang/Thread;)V
    ASTORE 4
   L4
    LINENUMBER 23 L4
    ALOAD 3
    INVOKESTATIC java/lang/Thread.currentThread ()Ljava/lang/Thread;
    INVOKESTATIC org/mpisws/runtime/RuntimeEnvironment.threadStart (Ljava/lang/Thread;Ljava/lang/Thread;)V
   L5
    LINENUMBER 24 L5
    ALOAD 4
    INVOKESTATIC java/lang/Thread.currentThread ()Ljava/lang/Thread;
    INVOKESTATIC org/mpisws/runtime/RuntimeEnvironment.threadStart (Ljava/lang/Thread;Ljava/lang/Thread;)V
   L6
    LINENUMBER 25 L6
    ALOAD 3
    DUP
    INVOKESTATIC java/lang/Thread.currentThread ()Ljava/lang/Thread;
    INVOKESTATIC org/mpisws/runtime/RuntimeEnvironment.threadJoin (Ljava/lang/Thread;Ljava/lang/Thread;)V
    INVOKEVIRTUAL org/mpisws/concurrent/programs/symbolic/counter/SymbolicCounter.join ()V
    INVOKESTATIC java/lang/Thread.currentThread ()Ljava/lang/Thread;
    INVOKESTATIC org/mpisws/runtime/RuntimeEnvironment.waitRequest (Ljava/lang/Thread;)V
   L7
    LINENUMBER 26 L7
    ALOAD 4
    DUP
    INVOKESTATIC java/lang/Thread.currentThread ()Ljava/lang/Thread;
    INVOKESTATIC org/mpisws/runtime/RuntimeEnvironment.threadJoin (Ljava/lang/Thread;Ljava/lang/Thread;)V
    INVOKEVIRTUAL org/mpisws/concurrent/programs/symbolic/counter/SymbolicCounter.join ()V
    INVOKESTATIC java/lang/Thread.currentThread ()Ljava/lang/Thread;
    INVOKESTATIC org/mpisws/runtime/RuntimeEnvironment.waitRequest (Ljava/lang/Thread;)V
   L8
    LINENUMBER 27 L8
    GETSTATIC org/mpisws/concurrent/programs/symbolic/counter/SymbolicCounter.$assertionsDisabled : Z
    IFNE L9
    ALOAD 2
    INVOKEVIRTUAL org/mpisws/concurrent/programs/symbolic/counter/Counter.getCount ()I
    ICONST_2
    IF_ICMPEQ L9
    NEW java/lang/AssertionError
    DUP
    ALOAD 2
    INVOKEVIRTUAL org/mpisws/concurrent/programs/symbolic/counter/Counter.getCount ()I
    INVOKEDYNAMIC makeConcatWithConstants(I)Ljava/lang/String; [
      // handle kind 0x6 : INVOKESTATIC
      java/lang/invoke/StringConcatFactory.makeConcatWithConstants(Ljava/lang/invoke/MethodHandles$Lookup;Ljava/lang/String;Ljava/lang/invoke/MethodType;Ljava/lang/String;[Ljava/lang/Object;)Ljava/lang/invoke/CallSite;
      // arguments:
      "Counter should be 2, but is \u0001"
    ]
    INVOKESTATIC org/mpisws/runtime/RuntimeEnvironment.assertOperation (Ljava/lang/String;)V
    INVOKESTATIC java/lang/Thread.currentThread ()Ljava/lang/Thread;
    INVOKESTATIC org/mpisws/runtime/RuntimeEnvironment.finishThreadRequest (Ljava/lang/Thread;)V
    RETURN
   L9
    LINENUMBER 28 L9
   FRAME FULL [[Ljava/lang/String; org/mpisws/symbolic/SymbolicInteger org/mpisws/concurrent/programs/symbolic/counter/Counter org/mpisws/concurrent/programs/symbolic/counter/SymbolicCounter org/mpisws/concurrent/programs/symbolic/counter/SymbolicCounter org/mpisws/runtime/SchedulerThread] []
    GETSTATIC java/lang/System.out : Ljava/io/PrintStream;
    LDC "If you see this message, the test passed!"
    INVOKEVIRTUAL java/io/PrintStream.println (Ljava/lang/String;)V
   L10
    LINENUMBER 29 L10
    INVOKESTATIC java/lang/Thread.currentThread ()Ljava/lang/Thread;
    INVOKESTATIC org/mpisws/runtime/RuntimeEnvironment.finishThreadRequest (Ljava/lang/Thread;)V
    RETURN
    MAXSTACK = 4
    MAXLOCALS = 6

  // access flags 0x8
  static <clinit>()V
   L0
    LINENUMBER 5 L0
    LDC Lorg/mpisws/concurrent/programs/symbolic/counter/SymbolicCounter;.class
    INVOKEVIRTUAL java/lang/Class.desiredAssertionStatus ()Z
    IFNE L1
    ICONST_1
    GOTO L2
   L1
   FRAME SAME
    ICONST_0
   L2
   FRAME SAME1 I
    PUTSTATIC org/mpisws/concurrent/programs/symbolic/counter/SymbolicCounter.$assertionsDisabled : Z
    RETURN
    MAXSTACK = 1
    MAXLOCALS = 0
}
