// class version 61.0 (61)
// access flags 0x21
public class org/mpisws/concurrent/programs/simple/counter/HelpingThread extends java/lang/Thread {

  // compiled from: HelpingThread.java

  // access flags 0x0
  Lorg/mpisws/concurrent/programs/simple/counter/Counter; counter

  // access flags 0x0
  <init>(Lorg/mpisws/concurrent/programs/simple/counter/Counter;)V
   L0
    LINENUMBER 7 L0
    ALOAD 0
    INVOKESPECIAL java/lang/Thread.<init> ()V
   L1
    LINENUMBER 8 L1
    ALOAD 0
    ALOAD 1
    DUP2
    INVOKESTATIC java/lang/Thread.currentThread ()Ljava/lang/Thread;
    LDC "org.mpisws.concurrent.programs.simple.counter.HelpingThread"
    LDC "counter"
    LDC "Lorg/mpisws/concurrent/programs/simple/counter/Counter;"
    INVOKESTATIC org/mpisws/runtime/RuntimeEnvironment.writeOperation (Ljava/lang/Object;Ljava/lang/Object;Ljava/lang/Thread;Ljava/lang/String;Ljava/lang/String;Ljava/lang/String;)V
    PUTFIELD org/mpisws/concurrent/programs/simple/counter/HelpingThread.counter : Lorg/mpisws/concurrent/programs/simple/counter/Counter;
    INVOKESTATIC java/lang/Thread.currentThread ()Ljava/lang/Thread;
    INVOKESTATIC org/mpisws/runtime/RuntimeEnvironment.waitRequest (Ljava/lang/Thread;)V
    NOP
   L2
    LINENUMBER 9 L2
    RETURN
    MAXSTACK = 8
    MAXLOCALS = 2

  // access flags 0x1
  public run()V
    INVOKESTATIC java/lang/Thread.currentThread ()Ljava/lang/Thread;
    INVOKESTATIC org/mpisws/runtime/RuntimeEnvironment.waitRequest (Ljava/lang/Thread;)V
   L0
    LINENUMBER 13 L0
    ALOAD 0
    DUP
    INVOKESTATIC java/lang/Thread.currentThread ()Ljava/lang/Thread;
    LDC "org.mpisws.concurrent.programs.simple.counter.HelpingThread"
    LDC "counter"
    LDC "Lorg/mpisws/concurrent/programs/simple/counter/Counter;"
    INVOKESTATIC org/mpisws/runtime/RuntimeEnvironment.readOperation (Ljava/lang/Object;Ljava/lang/Thread;Ljava/lang/String;Ljava/lang/String;Ljava/lang/String;)V
    GETFIELD org/mpisws/concurrent/programs/simple/counter/HelpingThread.counter : Lorg/mpisws/concurrent/programs/simple/counter/Counter;
    INVOKESTATIC java/lang/Thread.currentThread ()Ljava/lang/Thread;
    INVOKESTATIC org/mpisws/runtime/RuntimeEnvironment.waitRequest (Ljava/lang/Thread;)V
    NOP
    INVOKEVIRTUAL org/mpisws/concurrent/programs/simple/counter/Counter.increment ()V
   L1
    LINENUMBER 14 L1
    INVOKESTATIC java/lang/Thread.currentThread ()Ljava/lang/Thread;
    INVOKESTATIC org/mpisws/runtime/RuntimeEnvironment.finishThreadRequest (Ljava/lang/Thread;)V
    RETURN
    MAXSTACK = 6
    MAXLOCALS = 1
}
