// class version 61.0 (61)
// access flags 0x21
public class org/example/concurrent/programs/wrong/counter/BuggyCounter extends java/lang/Thread {

  // compiled from: BuggyCounter.java
  // access flags 0x19
  public final static INNERCLASS java/lang/invoke/MethodHandles$Lookup java/lang/invoke/MethodHandles Lookup

  // access flags 0x0
  Lorg/example/concurrent/programs/wrong/counter/Counter; counter1

  // access flags 0x0
  Lorg/example/concurrent/programs/wrong/counter/Counter; counter2

  // access flags 0x1
  public <init>(Lorg/example/concurrent/programs/wrong/counter/Counter;Lorg/example/concurrent/programs/wrong/counter/Counter;)V
   L0
    LINENUMBER 7 L0
    ALOAD 0
    INVOKESPECIAL java/lang/Thread.<init> ()V
   L1
    LINENUMBER 8 L1
    ALOAD 0
    ALOAD 1
    DUP2
    INVOKESTATIC java/lang/Thread.currentThread ()Ljava/lang/Thread;
    LDC "org.example.concurrent.programs.wrong.counter.BuggyCounter"
    LDC "counter1"
    LDC "Lorg/example/concurrent/programs/wrong/counter/Counter;"
    INVOKESTATIC org/example/runtime/RuntimeEnvironment.WriteOperation (Ljava/lang/Object;Ljava/lang/Object;Ljava/lang/Thread;Ljava/lang/String;Ljava/lang/String;Ljava/lang/String;)V
    PUTFIELD org/example/concurrent/programs/wrong/counter/BuggyCounter.counter1 : Lorg/example/concurrent/programs/wrong/counter/Counter;
   L2
    LINENUMBER 9 L2
    ALOAD 0
    ALOAD 2
    DUP2
    INVOKESTATIC java/lang/Thread.currentThread ()Ljava/lang/Thread;
    LDC "org.example.concurrent.programs.wrong.counter.BuggyCounter"
    LDC "counter2"
    LDC "Lorg/example/concurrent/programs/wrong/counter/Counter;"
    INVOKESTATIC org/example/runtime/RuntimeEnvironment.WriteOperation (Ljava/lang/Object;Ljava/lang/Object;Ljava/lang/Thread;Ljava/lang/String;Ljava/lang/String;Ljava/lang/String;)V
    PUTFIELD org/example/concurrent/programs/wrong/counter/BuggyCounter.counter2 : Lorg/example/concurrent/programs/wrong/counter/Counter;
   L3
    LINENUMBER 10 L3
    RETURN
    MAXSTACK = 8
    MAXLOCALS = 3

  // access flags 0x1
  public run()V
    TRYCATCHBLOCK L0 L1 L2 null
    TRYCATCHBLOCK L2 L3 L2 null
    TRYCATCHBLOCK L4 L5 L6 null
    TRYCATCHBLOCK L6 L7 L6 null
    INVOKESTATIC java/lang/Thread.currentThread ()Ljava/lang/Thread;
    INVOKESTATIC org/example/runtime/RuntimeEnvironment.waitRequest (Ljava/lang/Thread;)V
   L8
    LINENUMBER 13 L8
    ALOAD 0
    DUP
    INVOKESTATIC java/lang/Thread.currentThread ()Ljava/lang/Thread;
    LDC "org.example.concurrent.programs.wrong.counter.BuggyCounter"
    LDC "counter1"
    LDC "Lorg/example/concurrent/programs/wrong/counter/Counter;"
    INVOKESTATIC org/example/runtime/RuntimeEnvironment.ReadOperation (Ljava/lang/Object;Ljava/lang/Thread;Ljava/lang/String;Ljava/lang/String;Ljava/lang/String;)V
    GETFIELD org/example/concurrent/programs/wrong/counter/BuggyCounter.counter1 : Lorg/example/concurrent/programs/wrong/counter/Counter;
    DUP
    ASTORE 1
    ALOAD 1
    INVOKESTATIC java/lang/Thread.currentThread ()Ljava/lang/Thread;
    INVOKESTATIC org/example/runtime/RuntimeEnvironment.enterMonitor (Ljava/lang/Object;Ljava/lang/Thread;)V
    MONITORENTER
   L4
    LINENUMBER 14 L4
    ALOAD 1
    INVOKESTATIC java/lang/Thread.currentThread ()Ljava/lang/Thread;
    INVOKESTATIC org/example/runtime/RuntimeEnvironment.acquiredLock (Ljava/lang/Object;Ljava/lang/Thread;)V
    ALOAD 0
    DUP
    INVOKESTATIC java/lang/Thread.currentThread ()Ljava/lang/Thread;
    LDC "org.example.concurrent.programs.wrong.counter.BuggyCounter"
    LDC "counter1"
    LDC "Lorg/example/concurrent/programs/wrong/counter/Counter;"
    INVOKESTATIC org/example/runtime/RuntimeEnvironment.ReadOperation (Ljava/lang/Object;Ljava/lang/Thread;Ljava/lang/String;Ljava/lang/String;Ljava/lang/String;)V
    GETFIELD org/example/concurrent/programs/wrong/counter/BuggyCounter.counter1 : Lorg/example/concurrent/programs/wrong/counter/Counter;
    DUP
    DUP
    INVOKESTATIC java/lang/Thread.currentThread ()Ljava/lang/Thread;
    LDC "org.example.concurrent.programs.wrong.counter.Counter"
    LDC "count"
    LDC "I"
    INVOKESTATIC org/example/runtime/RuntimeEnvironment.ReadOperation (Ljava/lang/Object;Ljava/lang/Thread;Ljava/lang/String;Ljava/lang/String;Ljava/lang/String;)V
    GETFIELD org/example/concurrent/programs/wrong/counter/Counter.count : I
    ICONST_1
    IADD
    DUP2
    INVOKESTATIC java/lang/Integer.valueOf (I)Ljava/lang/Integer;
    INVOKESTATIC java/lang/Thread.currentThread ()Ljava/lang/Thread;
    LDC "org.example.concurrent.programs.wrong.counter.Counter"
    LDC "count"
    LDC "I"
    INVOKESTATIC org/example/runtime/RuntimeEnvironment.WriteOperation (Ljava/lang/Object;Ljava/lang/Object;Ljava/lang/Thread;Ljava/lang/String;Ljava/lang/String;Ljava/lang/String;)V
    PUTFIELD org/example/concurrent/programs/wrong/counter/Counter.count : I
   L9
    LINENUMBER 15 L9
    GETSTATIC java/lang/System.out : Ljava/io/PrintStream;
    ALOAD 0
    INVOKEVIRTUAL org/example/concurrent/programs/wrong/counter/BuggyCounter.getName ()Ljava/lang/String;
    ALOAD 0
    DUP
    INVOKESTATIC java/lang/Thread.currentThread ()Ljava/lang/Thread;
    LDC "org.example.concurrent.programs.wrong.counter.BuggyCounter"
    LDC "counter1"
    LDC "Lorg/example/concurrent/programs/wrong/counter/Counter;"
    INVOKESTATIC org/example/runtime/RuntimeEnvironment.ReadOperation (Ljava/lang/Object;Ljava/lang/Thread;Ljava/lang/String;Ljava/lang/String;Ljava/lang/String;)V
    GETFIELD org/example/concurrent/programs/wrong/counter/BuggyCounter.counter1 : Lorg/example/concurrent/programs/wrong/counter/Counter;
    DUP
    INVOKESTATIC java/lang/Thread.currentThread ()Ljava/lang/Thread;
    LDC "org.example.concurrent.programs.wrong.counter.Counter"
    LDC "count"
    LDC "I"
    INVOKESTATIC org/example/runtime/RuntimeEnvironment.ReadOperation (Ljava/lang/Object;Ljava/lang/Thread;Ljava/lang/String;Ljava/lang/String;Ljava/lang/String;)V
    GETFIELD org/example/concurrent/programs/wrong/counter/Counter.count : I
    INVOKEDYNAMIC makeConcatWithConstants(Ljava/lang/String;I)Ljava/lang/String; [
      // handle kind 0x6 : INVOKESTATIC
      java/lang/invoke/StringConcatFactory.makeConcatWithConstants(Ljava/lang/invoke/MethodHandles$Lookup;Ljava/lang/String;Ljava/lang/invoke/MethodType;Ljava/lang/String;[Ljava/lang/Object;)Ljava/lang/invoke/CallSite;
      // arguments:
      "[\u0001 message] : The counter1 value is \u0001"
    ]
    INVOKEVIRTUAL java/io/PrintStream.println (Ljava/lang/String;)V
   L10
    LINENUMBER 16 L10
    ALOAD 0
    DUP
    INVOKESTATIC java/lang/Thread.currentThread ()Ljava/lang/Thread;
    LDC "org.example.concurrent.programs.wrong.counter.BuggyCounter"
    LDC "counter2"
    LDC "Lorg/example/concurrent/programs/wrong/counter/Counter;"
    INVOKESTATIC org/example/runtime/RuntimeEnvironment.ReadOperation (Ljava/lang/Object;Ljava/lang/Thread;Ljava/lang/String;Ljava/lang/String;Ljava/lang/String;)V
    GETFIELD org/example/concurrent/programs/wrong/counter/BuggyCounter.counter2 : Lorg/example/concurrent/programs/wrong/counter/Counter;
    DUP
    ASTORE 2
    ALOAD 2
    INVOKESTATIC java/lang/Thread.currentThread ()Ljava/lang/Thread;
    INVOKESTATIC org/example/runtime/RuntimeEnvironment.enterMonitor (Ljava/lang/Object;Ljava/lang/Thread;)V
    MONITORENTER
   L0
    LINENUMBER 17 L0
    ALOAD 2
    INVOKESTATIC java/lang/Thread.currentThread ()Ljava/lang/Thread;
    INVOKESTATIC org/example/runtime/RuntimeEnvironment.acquiredLock (Ljava/lang/Object;Ljava/lang/Thread;)V
    ALOAD 0
    DUP
    INVOKESTATIC java/lang/Thread.currentThread ()Ljava/lang/Thread;
    LDC "org.example.concurrent.programs.wrong.counter.BuggyCounter"
    LDC "counter2"
    LDC "Lorg/example/concurrent/programs/wrong/counter/Counter;"
    INVOKESTATIC org/example/runtime/RuntimeEnvironment.ReadOperation (Ljava/lang/Object;Ljava/lang/Thread;Ljava/lang/String;Ljava/lang/String;Ljava/lang/String;)V
    GETFIELD org/example/concurrent/programs/wrong/counter/BuggyCounter.counter2 : Lorg/example/concurrent/programs/wrong/counter/Counter;
    DUP
    DUP
    INVOKESTATIC java/lang/Thread.currentThread ()Ljava/lang/Thread;
    LDC "org.example.concurrent.programs.wrong.counter.Counter"
    LDC "count"
    LDC "I"
    INVOKESTATIC org/example/runtime/RuntimeEnvironment.ReadOperation (Ljava/lang/Object;Ljava/lang/Thread;Ljava/lang/String;Ljava/lang/String;Ljava/lang/String;)V
    GETFIELD org/example/concurrent/programs/wrong/counter/Counter.count : I
    ICONST_1
    IADD
    DUP2
    INVOKESTATIC java/lang/Integer.valueOf (I)Ljava/lang/Integer;
    INVOKESTATIC java/lang/Thread.currentThread ()Ljava/lang/Thread;
    LDC "org.example.concurrent.programs.wrong.counter.Counter"
    LDC "count"
    LDC "I"
    INVOKESTATIC org/example/runtime/RuntimeEnvironment.WriteOperation (Ljava/lang/Object;Ljava/lang/Object;Ljava/lang/Thread;Ljava/lang/String;Ljava/lang/String;Ljava/lang/String;)V
    PUTFIELD org/example/concurrent/programs/wrong/counter/Counter.count : I
   L11
    LINENUMBER 18 L11
    GETSTATIC java/lang/System.out : Ljava/io/PrintStream;
    ALOAD 0
    INVOKEVIRTUAL org/example/concurrent/programs/wrong/counter/BuggyCounter.getName ()Ljava/lang/String;
    ALOAD 0
    DUP
    INVOKESTATIC java/lang/Thread.currentThread ()Ljava/lang/Thread;
    LDC "org.example.concurrent.programs.wrong.counter.BuggyCounter"
    LDC "counter1"
    LDC "Lorg/example/concurrent/programs/wrong/counter/Counter;"
    INVOKESTATIC org/example/runtime/RuntimeEnvironment.ReadOperation (Ljava/lang/Object;Ljava/lang/Thread;Ljava/lang/String;Ljava/lang/String;Ljava/lang/String;)V
    GETFIELD org/example/concurrent/programs/wrong/counter/BuggyCounter.counter1 : Lorg/example/concurrent/programs/wrong/counter/Counter;
    DUP
    INVOKESTATIC java/lang/Thread.currentThread ()Ljava/lang/Thread;
    LDC "org.example.concurrent.programs.wrong.counter.Counter"
    LDC "count"
    LDC "I"
    INVOKESTATIC org/example/runtime/RuntimeEnvironment.ReadOperation (Ljava/lang/Object;Ljava/lang/Thread;Ljava/lang/String;Ljava/lang/String;Ljava/lang/String;)V
    GETFIELD org/example/concurrent/programs/wrong/counter/Counter.count : I
    INVOKEDYNAMIC makeConcatWithConstants(Ljava/lang/String;I)Ljava/lang/String; [
      // handle kind 0x6 : INVOKESTATIC
      java/lang/invoke/StringConcatFactory.makeConcatWithConstants(Ljava/lang/invoke/MethodHandles$Lookup;Ljava/lang/String;Ljava/lang/invoke/MethodType;Ljava/lang/String;[Ljava/lang/Object;)Ljava/lang/invoke/CallSite;
      // arguments:
      "[\u0001 message] : The counter2 value is \u0001"
    ]
    INVOKEVIRTUAL java/io/PrintStream.println (Ljava/lang/String;)V
   L12
    LINENUMBER 19 L12
    ALOAD 2
    ALOAD 2
    INVOKESTATIC java/lang/Thread.currentThread ()Ljava/lang/Thread;
    INVOKESTATIC org/example/runtime/RuntimeEnvironment.exitMonitor (Ljava/lang/Object;Ljava/lang/Thread;)V
    MONITOREXIT
   L1
    GOTO L13
   L2
   FRAME FULL [org/example/concurrent/programs/wrong/counter/BuggyCounter org/example/concurrent/programs/wrong/counter/Counter org/example/concurrent/programs/wrong/counter/Counter] [java/lang/Throwable]
    ASTORE 3
    ALOAD 2
    ALOAD 2
    INVOKESTATIC java/lang/Thread.currentThread ()Ljava/lang/Thread;
    INVOKESTATIC org/example/runtime/RuntimeEnvironment.exitMonitor (Ljava/lang/Object;Ljava/lang/Thread;)V
    MONITOREXIT
   L3
    ALOAD 3
    INVOKESTATIC java/lang/Thread.currentThread ()Ljava/lang/Thread;
    INVOKESTATIC org/example/runtime/RuntimeEnvironment.finishThreadRequest (Ljava/lang/Thread;)V
    ATHROW
   L13
    LINENUMBER 20 L13
   FRAME SAME
    ALOAD 2
    INVOKESTATIC java/lang/Thread.currentThread ()Ljava/lang/Thread;
    INVOKESTATIC org/example/runtime/RuntimeEnvironment.releasedLock (Ljava/lang/Object;Ljava/lang/Thread;)V
    ALOAD 1
    ALOAD 1
    INVOKESTATIC java/lang/Thread.currentThread ()Ljava/lang/Thread;
    INVOKESTATIC org/example/runtime/RuntimeEnvironment.exitMonitor (Ljava/lang/Object;Ljava/lang/Thread;)V
    MONITOREXIT
   L5
    GOTO L14
   L6
   FRAME FULL [org/example/concurrent/programs/wrong/counter/BuggyCounter org/example/concurrent/programs/wrong/counter/Counter] [java/lang/Throwable]
    ASTORE 4
    ALOAD 1
    ALOAD 1
    INVOKESTATIC java/lang/Thread.currentThread ()Ljava/lang/Thread;
    INVOKESTATIC org/example/runtime/RuntimeEnvironment.exitMonitor (Ljava/lang/Object;Ljava/lang/Thread;)V
    MONITOREXIT
   L7
    ALOAD 4
    INVOKESTATIC java/lang/Thread.currentThread ()Ljava/lang/Thread;
    INVOKESTATIC org/example/runtime/RuntimeEnvironment.finishThreadRequest (Ljava/lang/Thread;)V
    ATHROW
   L14
    LINENUMBER 21 L14
   FRAME APPEND [org/example/concurrent/programs/wrong/counter/Counter]
    ALOAD 1
    INVOKESTATIC java/lang/Thread.currentThread ()Ljava/lang/Thread;
    INVOKESTATIC org/example/runtime/RuntimeEnvironment.releasedLock (Ljava/lang/Object;Ljava/lang/Thread;)V
    INVOKESTATIC java/lang/Thread.currentThread ()Ljava/lang/Thread;
    INVOKESTATIC org/example/runtime/RuntimeEnvironment.finishThreadRequest (Ljava/lang/Thread;)V
    RETURN
    MAXSTACK = 8
    MAXLOCALS = 5

  // access flags 0x9
  public static main([Ljava/lang/String;)V
    INVOKESTATIC java/lang/Thread.currentThread ()Ljava/lang/Thread;
    INVOKESTATIC org/example/runtime/RuntimeEnvironment.init (Ljava/lang/Thread;)V
    NEW org/example/runtime/SchedulerThread
    DUP
    INVOKESPECIAL org/example/runtime/SchedulerThread.<init> ()V
    ASTORE 5
    ALOAD 5
    LDC "SchedulerThread"
    INVOKEVIRTUAL org/example/runtime/SchedulerThread.setName (Ljava/lang/String;)V
    INVOKESTATIC java/lang/Thread.currentThread ()Ljava/lang/Thread;
    ALOAD 5
    INVOKESTATIC org/example/runtime/RuntimeEnvironment.initSchedulerThread (Ljava/lang/Thread;Ljava/lang/Thread;)V
   L0
    LINENUMBER 23 L0
    NEW org/example/concurrent/programs/wrong/counter/Counter
    DUP
    INVOKESPECIAL org/example/concurrent/programs/wrong/counter/Counter.<init> ()V
    ASTORE 1
   L1
    LINENUMBER 24 L1
    NEW org/example/concurrent/programs/wrong/counter/Counter
    DUP
    INVOKESPECIAL org/example/concurrent/programs/wrong/counter/Counter.<init> ()V
    ASTORE 2
   L2
    LINENUMBER 25 L2
    NEW org/example/concurrent/programs/wrong/counter/BuggyCounter
    DUP
    ALOAD 1
    ALOAD 2
    INVOKESPECIAL org/example/concurrent/programs/wrong/counter/BuggyCounter.<init> (Lorg/example/concurrent/programs/wrong/counter/Counter;Lorg/example/concurrent/programs/wrong/counter/Counter;)V
    ASTORE 3
    ALOAD 3
    INVOKESTATIC org/example/runtime/RuntimeEnvironment.addThread (Ljava/lang/Thread;)V
   L3
    LINENUMBER 26 L3
    NEW org/example/concurrent/programs/wrong/counter/BuggyCounter
    DUP
    ALOAD 2
    ALOAD 1
    INVOKESPECIAL org/example/concurrent/programs/wrong/counter/BuggyCounter.<init> (Lorg/example/concurrent/programs/wrong/counter/Counter;Lorg/example/concurrent/programs/wrong/counter/Counter;)V
    ASTORE 4
    ALOAD 4
    INVOKESTATIC org/example/runtime/RuntimeEnvironment.addThread (Ljava/lang/Thread;)V
   L4
    LINENUMBER 27 L4
    ALOAD 3
    INVOKESTATIC java/lang/Thread.currentThread ()Ljava/lang/Thread;
    ALOAD 3
    INVOKESTATIC org/example/runtime/RuntimeEnvironment.threadStart (Ljava/lang/Thread;Ljava/lang/Thread;)V
   L5
    LINENUMBER 28 L5
    ALOAD 4
    INVOKESTATIC java/lang/Thread.currentThread ()Ljava/lang/Thread;
    ALOAD 4
    INVOKESTATIC org/example/runtime/RuntimeEnvironment.threadStart (Ljava/lang/Thread;Ljava/lang/Thread;)V
   L6
    LINENUMBER 29 L6
    INVOKESTATIC java/lang/Thread.currentThread ()Ljava/lang/Thread;
    INVOKESTATIC org/example/runtime/RuntimeEnvironment.finishThreadRequest (Ljava/lang/Thread;)V
    RETURN
    MAXSTACK = 4
    MAXLOCALS = 6
}
