// class version 61.0 (61)
// access flags 0x21
public class org/mpisws/concurrent/programs/tagged/message/ReceiverThread extends org/mpisws/util/concurrent/JMCThread {

  // compiled from: ReceiverThread.java
  // access flags 0x19
  public final static INNERCLASS java/lang/invoke/MethodHandles$Lookup java/lang/invoke/MethodHandles Lookup

  // access flags 0x0
  J knownThread

  // access flags 0x0
  J knownTag

  // access flags 0x1
  public <init>()V
   L0
    LINENUMBER 6 L0
    ALOAD 0
    INVOKESPECIAL org/mpisws/util/concurrent/JMCThread.<init> ()V
   L1
    LINENUMBER 8 L1
    ALOAD 0
    LDC 100
    PUTFIELD org/mpisws/concurrent/programs/tagged/message/ReceiverThread.knownTag : J
    RETURN
    MAXSTACK = 3
    MAXLOCALS = 1

  // access flags 0x1
  public run()V
    INVOKESTATIC java/lang/Thread.currentThread ()Ljava/lang/Thread;
    INVOKESTATIC org/mpisws/runtime/RuntimeEnvironment.waitRequest (Ljava/lang/Thread;)V
   L0
    LINENUMBER 12 L0
    ALOAD 0
    INVOKEDYNAMIC apply(Lorg/mpisws/concurrent/programs/tagged/message/ReceiverThread;)Ljava/util/function/BiFunction; [
      // handle kind 0x6 : INVOKESTATIC
      java/lang/invoke/LambdaMetafactory.metafactory(Ljava/lang/invoke/MethodHandles$Lookup;Ljava/lang/String;Ljava/lang/invoke/MethodType;Ljava/lang/invoke/MethodType;Ljava/lang/invoke/MethodHandle;Ljava/lang/invoke/MethodType;)Ljava/lang/invoke/CallSite;
      // arguments:
      (Ljava/lang/Object;Ljava/lang/Object;)Ljava/lang/Object;, 
      // handle kind 0x5 : INVOKEVIRTUAL
      org/mpisws/concurrent/programs/tagged/message/ReceiverThread.lambda$run$0(Ljava/lang/Long;Ljava/lang/Long;)Ljava/lang/Boolean;, 
      (Ljava/lang/Long;Ljava/lang/Long;)Ljava/lang/Boolean;
    ]
    INVOKESTATIC org/mpisws/util/concurrent/MessageServer.recv_tagged_msg_unblock (Ljava/util/function/BiFunction;)Ljava/lang/Object;
    ASTORE 1
   L1
    LINENUMBER 13 L1
    GETSTATIC java/lang/System.out : Ljava/io/PrintStream;
    ALOAD 1
    INVOKEDYNAMIC makeConcatWithConstants(Ljava/lang/Object;)Ljava/lang/String; [
      // handle kind 0x6 : INVOKESTATIC
      java/lang/invoke/StringConcatFactory.makeConcatWithConstants(Ljava/lang/invoke/MethodHandles$Lookup;Ljava/lang/String;Ljava/lang/invoke/MethodType;Ljava/lang/String;[Ljava/lang/Object;)Ljava/lang/invoke/CallSite;
      // arguments:
      "Value of the message is : \u0001"
    ]
    INVOKEVIRTUAL java/io/PrintStream.println (Ljava/lang/String;)V
   L2
    LINENUMBER 14 L2
    GETSTATIC java/lang/System.out : Ljava/io/PrintStream;
    INVOKESTATIC java/lang/Thread.currentThread ()Ljava/lang/Thread;
    INVOKEVIRTUAL java/lang/Thread.getId ()J
    INVOKEVIRTUAL java/io/PrintStream.println (J)V
   L3
    LINENUMBER 15 L3
    INVOKESTATIC java/lang/Thread.currentThread ()Ljava/lang/Thread;
    INVOKESTATIC org/mpisws/runtime/RuntimeEnvironment.finishThreadRequest (Ljava/lang/Thread;)V
    RETURN
    MAXSTACK = 3
    MAXLOCALS = 2

  // access flags 0x1002
  private synthetic lambda$run$0(Ljava/lang/Long;Ljava/lang/Long;)Ljava/lang/Boolean;
   L0
    LINENUMBER 12 L0
    ALOAD 2
    INVOKEVIRTUAL java/lang/Long.longValue ()J
    ALOAD 0
    GETFIELD org/mpisws/concurrent/programs/tagged/message/ReceiverThread.knownTag : J
    LCMP
    IFNE L1
    ALOAD 1
    INVOKEVIRTUAL java/lang/Long.longValue ()J
    INVOKESTATIC java/lang/Thread.currentThread ()Ljava/lang/Thread;
    INVOKEVIRTUAL java/lang/Thread.getId ()J
    LCMP
    IFNE L1
    ICONST_1
    GOTO L2
   L1
   FRAME SAME
    ICONST_0
   L2
   FRAME SAME1 I
    INVOKESTATIC java/lang/Boolean.valueOf (Z)Ljava/lang/Boolean;
    ARETURN
    MAXSTACK = 4
    MAXLOCALS = 3
}
