// class version 61.0 (61)
// access flags 0x21
public class org/example/concurrent/programs/complex/counter/Dummy {

  // compiled from: Dummy.java

  // access flags 0x1
  public <init>()V
   L0
    LINENUMBER 3 L0
    ALOAD 0
    INVOKESPECIAL java/lang/Object.<init> ()V
    RETURN
    MAXSTACK = 1
    MAXLOCALS = 1

  // access flags 0x1
  public exe()V
   L0
    LINENUMBER 6 L0
    NEW org/example/concurrent/programs/complex/counter/Counter
    DUP
    INVOKESPECIAL org/example/concurrent/programs/complex/counter/Counter.<init> ()V
    ASTORE 1
   L1
    LINENUMBER 7 L1
    NEW org/example/concurrent/programs/complex/counter/CounterThread
    DUP
    ALOAD 1
    INVOKESPECIAL org/example/concurrent/programs/complex/counter/CounterThread.<init> (Lorg/example/concurrent/programs/complex/counter/Counter;)V
    ASTORE 2
    ALOAD 2
    INVOKESTATIC org/example/runtime/RuntimeEnvironment.addThread (Ljava/lang/Thread;)V
   L2
    LINENUMBER 8 L2
    ALOAD 2
    LDC "Thread 1"
    INVOKEVIRTUAL org/example/concurrent/programs/complex/counter/CounterThread.setName (Ljava/lang/String;)V
   L3
    LINENUMBER 9 L3
    NEW org/example/concurrent/programs/complex/counter/CounterThread
    DUP
    ALOAD 1
    INVOKESPECIAL org/example/concurrent/programs/complex/counter/CounterThread.<init> (Lorg/example/concurrent/programs/complex/counter/Counter;)V
    ASTORE 3
    ALOAD 3
    INVOKESTATIC org/example/runtime/RuntimeEnvironment.addThread (Ljava/lang/Thread;)V
   L4
    LINENUMBER 10 L4
    ALOAD 3
    LDC "Thread 2"
    INVOKEVIRTUAL org/example/concurrent/programs/complex/counter/CounterThread.setName (Ljava/lang/String;)V
   L5
    LINENUMBER 11 L5
    ALOAD 2
    INVOKEVIRTUAL org/example/concurrent/programs/complex/counter/CounterThread.exe ()V
   L6
    LINENUMBER 12 L6
    ALOAD 3
    INVOKEVIRTUAL org/example/concurrent/programs/complex/counter/CounterThread.exe ()V
   L7
    LINENUMBER 13 L7
    RETURN
    MAXSTACK = 3
    MAXLOCALS = 4
}
