// class version 61.0 (61)
// access flags 0x21
public class org/mpisws/concurrent/programs/wrong/counter/BuggyCounter extends java/lang/Thread {

  // compiled from: BuggyCounter.java
  // access flags 0x19
  public final static INNERCLASS java/lang/invoke/MethodHandles$Lookup java/lang/invoke/MethodHandles Lookup

  // access flags 0x0
  Lorg/mpisws/concurrent/programs/wrong/counter/Counter; counter1

  // access flags 0x0
  Lorg/mpisws/concurrent/programs/wrong/counter/Counter; counter2

  // access flags 0x1
  public <init>(Lorg/mpisws/concurrent/programs/wrong/counter/Counter;Lorg/mpisws/concurrent/programs/wrong/counter/Counter;)V
   L0
    LINENUMBER 7 L0
    ALOAD 0
    INVOKESPECIAL java/lang/Thread.<init> ()V
   L1
    LINENUMBER 8 L1
    ALOAD 0
    ALOAD 1
    PUTFIELD org/mpisws/concurrent/programs/wrong/counter/BuggyCounter.counter1 : Lorg/mpisws/concurrent/programs/wrong/counter/Counter;
   L2
    LINENUMBER 9 L2
    ALOAD 0
    ALOAD 2
    PUTFIELD org/mpisws/concurrent/programs/wrong/counter/BuggyCounter.counter2 : Lorg/mpisws/concurrent/programs/wrong/counter/Counter;
   L3
    LINENUMBER 10 L3
    RETURN
    MAXSTACK = 2
    MAXLOCALS = 3

  // access flags 0x1
  public run()V
    TRYCATCHBLOCK L0 L1 L2 null
    TRYCATCHBLOCK L2 L3 L2 null
    TRYCATCHBLOCK L4 L5 L6 null
    TRYCATCHBLOCK L6 L7 L6 null
    INVOKESTATIC java/lang/Thread.currentThread ()Ljava/lang/Thread;
    INVOKESTATIC org/mpisws/runtime/RuntimeEnvironment.waitRequest (Ljava/lang/Thread;)V
   L8
    LINENUMBER 13 L8
    ALOAD 0
    GETFIELD org/mpisws/concurrent/programs/wrong/counter/BuggyCounter.counter1 : Lorg/mpisws/concurrent/programs/wrong/counter/Counter;
    DUP
    ASTORE 1
    DUP
    DUP
    INVOKESTATIC java/lang/Thread.currentThread ()Ljava/lang/Thread;
    INVOKESTATIC org/mpisws/runtime/RuntimeEnvironment.enterMonitor (Ljava/lang/Object;Ljava/lang/Thread;)V
    MONITORENTER
   L4
    LINENUMBER 14 L4
    INVOKESTATIC java/lang/Thread.currentThread ()Ljava/lang/Thread;
    INVOKESTATIC org/mpisws/runtime/RuntimeEnvironment.acquiredLock (Ljava/lang/Object;Ljava/lang/Thread;)V
    INVOKESTATIC java/lang/Thread.currentThread ()Ljava/lang/Thread;
    INVOKESTATIC org/mpisws/runtime/RuntimeEnvironment.waitRequest (Ljava/lang/Thread;)V
    ALOAD 0
    GETFIELD org/mpisws/concurrent/programs/wrong/counter/BuggyCounter.counter1 : Lorg/mpisws/concurrent/programs/wrong/counter/Counter;
    DUP
    DUP
    INVOKESTATIC java/lang/Thread.currentThread ()Ljava/lang/Thread;
    LDC "org.mpisws.concurrent.programs.wrong.counter.Counter"
    LDC "count"
    LDC "I"
    INVOKESTATIC org/mpisws/runtime/RuntimeEnvironment.readOperation (Ljava/lang/Object;Ljava/lang/Thread;Ljava/lang/String;Ljava/lang/String;Ljava/lang/String;)V
    GETFIELD org/mpisws/concurrent/programs/wrong/counter/Counter.count : I
    INVOKESTATIC java/lang/Thread.currentThread ()Ljava/lang/Thread;
    INVOKESTATIC org/mpisws/runtime/RuntimeEnvironment.waitRequest (Ljava/lang/Thread;)V
    NOP
    ICONST_1
    IADD
    DUP2
    INVOKESTATIC java/lang/Integer.valueOf (I)Ljava/lang/Integer;
    INVOKESTATIC java/lang/Thread.currentThread ()Ljava/lang/Thread;
    LDC "org.mpisws.concurrent.programs.wrong.counter.Counter"
    LDC "count"
    LDC "I"
    INVOKESTATIC org/mpisws/runtime/RuntimeEnvironment.writeOperation (Ljava/lang/Object;Ljava/lang/Object;Ljava/lang/Thread;Ljava/lang/String;Ljava/lang/String;Ljava/lang/String;)V
    PUTFIELD org/mpisws/concurrent/programs/wrong/counter/Counter.count : I
    INVOKESTATIC java/lang/Thread.currentThread ()Ljava/lang/Thread;
    INVOKESTATIC org/mpisws/runtime/RuntimeEnvironment.waitRequest (Ljava/lang/Thread;)V
    NOP
   L9
    LINENUMBER 15 L9
    GETSTATIC java/lang/System.out : Ljava/io/PrintStream;
    ALOAD 0
    INVOKEVIRTUAL org/mpisws/concurrent/programs/wrong/counter/BuggyCounter.getName ()Ljava/lang/String;
    ALOAD 0
    GETFIELD org/mpisws/concurrent/programs/wrong/counter/BuggyCounter.counter1 : Lorg/mpisws/concurrent/programs/wrong/counter/Counter;
    DUP
    INVOKESTATIC java/lang/Thread.currentThread ()Ljava/lang/Thread;
    LDC "org.mpisws.concurrent.programs.wrong.counter.Counter"
    LDC "count"
    LDC "I"
    INVOKESTATIC org/mpisws/runtime/RuntimeEnvironment.readOperation (Ljava/lang/Object;Ljava/lang/Thread;Ljava/lang/String;Ljava/lang/String;Ljava/lang/String;)V
    GETFIELD org/mpisws/concurrent/programs/wrong/counter/Counter.count : I
    INVOKESTATIC java/lang/Thread.currentThread ()Ljava/lang/Thread;
    INVOKESTATIC org/mpisws/runtime/RuntimeEnvironment.waitRequest (Ljava/lang/Thread;)V
    NOP
    INVOKEDYNAMIC makeConcatWithConstants(Ljava/lang/String;I)Ljava/lang/String; [
      // handle kind 0x6 : INVOKESTATIC
      java/lang/invoke/StringConcatFactory.makeConcatWithConstants(Ljava/lang/invoke/MethodHandles$Lookup;Ljava/lang/String;Ljava/lang/invoke/MethodType;Ljava/lang/String;[Ljava/lang/Object;)Ljava/lang/invoke/CallSite;
      // arguments:
      "[\u0001 message] : The counter1 value is \u0001"
    ]
    INVOKEVIRTUAL java/io/PrintStream.println (Ljava/lang/String;)V
   L10
    LINENUMBER 16 L10
    ALOAD 0
    GETFIELD org/mpisws/concurrent/programs/wrong/counter/BuggyCounter.counter2 : Lorg/mpisws/concurrent/programs/wrong/counter/Counter;
    DUP
    ASTORE 2
    DUP
    DUP
    INVOKESTATIC java/lang/Thread.currentThread ()Ljava/lang/Thread;
    INVOKESTATIC org/mpisws/runtime/RuntimeEnvironment.enterMonitor (Ljava/lang/Object;Ljava/lang/Thread;)V
    MONITORENTER
   L0
    LINENUMBER 18 L0
    INVOKESTATIC java/lang/Thread.currentThread ()Ljava/lang/Thread;
    INVOKESTATIC org/mpisws/runtime/RuntimeEnvironment.acquiredLock (Ljava/lang/Object;Ljava/lang/Thread;)V
    INVOKESTATIC java/lang/Thread.currentThread ()Ljava/lang/Thread;
    INVOKESTATIC org/mpisws/runtime/RuntimeEnvironment.waitRequest (Ljava/lang/Thread;)V
    ALOAD 0
    GETFIELD org/mpisws/concurrent/programs/wrong/counter/BuggyCounter.counter2 : Lorg/mpisws/concurrent/programs/wrong/counter/Counter;
    DUP
    DUP
    INVOKESTATIC java/lang/Thread.currentThread ()Ljava/lang/Thread;
    LDC "org.mpisws.concurrent.programs.wrong.counter.Counter"
    LDC "count"
    LDC "I"
    INVOKESTATIC org/mpisws/runtime/RuntimeEnvironment.readOperation (Ljava/lang/Object;Ljava/lang/Thread;Ljava/lang/String;Ljava/lang/String;Ljava/lang/String;)V
    GETFIELD org/mpisws/concurrent/programs/wrong/counter/Counter.count : I
    INVOKESTATIC java/lang/Thread.currentThread ()Ljava/lang/Thread;
    INVOKESTATIC org/mpisws/runtime/RuntimeEnvironment.waitRequest (Ljava/lang/Thread;)V
    NOP
    ICONST_1
    IADD
    DUP2
    INVOKESTATIC java/lang/Integer.valueOf (I)Ljava/lang/Integer;
    INVOKESTATIC java/lang/Thread.currentThread ()Ljava/lang/Thread;
    LDC "org.mpisws.concurrent.programs.wrong.counter.Counter"
    LDC "count"
    LDC "I"
    INVOKESTATIC org/mpisws/runtime/RuntimeEnvironment.writeOperation (Ljava/lang/Object;Ljava/lang/Object;Ljava/lang/Thread;Ljava/lang/String;Ljava/lang/String;Ljava/lang/String;)V
    PUTFIELD org/mpisws/concurrent/programs/wrong/counter/Counter.count : I
    INVOKESTATIC java/lang/Thread.currentThread ()Ljava/lang/Thread;
    INVOKESTATIC org/mpisws/runtime/RuntimeEnvironment.waitRequest (Ljava/lang/Thread;)V
    NOP
   L11
    LINENUMBER 19 L11
    GETSTATIC java/lang/System.out : Ljava/io/PrintStream;
    ALOAD 0
    INVOKEVIRTUAL org/mpisws/concurrent/programs/wrong/counter/BuggyCounter.getName ()Ljava/lang/String;
    ALOAD 0
    GETFIELD org/mpisws/concurrent/programs/wrong/counter/BuggyCounter.counter1 : Lorg/mpisws/concurrent/programs/wrong/counter/Counter;
    DUP
    INVOKESTATIC java/lang/Thread.currentThread ()Ljava/lang/Thread;
    LDC "org.mpisws.concurrent.programs.wrong.counter.Counter"
    LDC "count"
    LDC "I"
    INVOKESTATIC org/mpisws/runtime/RuntimeEnvironment.readOperation (Ljava/lang/Object;Ljava/lang/Thread;Ljava/lang/String;Ljava/lang/String;Ljava/lang/String;)V
    GETFIELD org/mpisws/concurrent/programs/wrong/counter/Counter.count : I
    INVOKESTATIC java/lang/Thread.currentThread ()Ljava/lang/Thread;
    INVOKESTATIC org/mpisws/runtime/RuntimeEnvironment.waitRequest (Ljava/lang/Thread;)V
    NOP
    INVOKEDYNAMIC makeConcatWithConstants(Ljava/lang/String;I)Ljava/lang/String; [
      // handle kind 0x6 : INVOKESTATIC
      java/lang/invoke/StringConcatFactory.makeConcatWithConstants(Ljava/lang/invoke/MethodHandles$Lookup;Ljava/lang/String;Ljava/lang/invoke/MethodType;Ljava/lang/String;[Ljava/lang/Object;)Ljava/lang/invoke/CallSite;
      // arguments:
      "[\u0001 message] : The counter2 value is \u0001"
    ]
    INVOKEVIRTUAL java/io/PrintStream.println (Ljava/lang/String;)V
   L12
    LINENUMBER 21 L12
    ALOAD 2
    DUP
    DUP
    INVOKESTATIC java/lang/Thread.currentThread ()Ljava/lang/Thread;
    INVOKESTATIC org/mpisws/runtime/RuntimeEnvironment.exitMonitor (Ljava/lang/Object;Ljava/lang/Thread;)V
    MONITOREXIT
   L1
    GOTO L13
   L2
   FRAME FULL [org/mpisws/concurrent/programs/wrong/counter/BuggyCounter org/mpisws/concurrent/programs/wrong/counter/Counter org/mpisws/concurrent/programs/wrong/counter/Counter] [java/lang/Throwable]
    ASTORE 3
    ALOAD 2
    DUP
    DUP
    INVOKESTATIC java/lang/Thread.currentThread ()Ljava/lang/Thread;
    INVOKESTATIC org/mpisws/runtime/RuntimeEnvironment.exitMonitor (Ljava/lang/Object;Ljava/lang/Thread;)V
    MONITOREXIT
   L3
    ALOAD 3
    ATHROW
   L13
    LINENUMBER 22 L13
   FRAME SAME1 org/mpisws/concurrent/programs/wrong/counter/Counter
    INVOKESTATIC java/lang/Thread.currentThread ()Ljava/lang/Thread;
    INVOKESTATIC org/mpisws/runtime/RuntimeEnvironment.releasedLock (Ljava/lang/Object;Ljava/lang/Thread;)V
    INVOKESTATIC java/lang/Thread.currentThread ()Ljava/lang/Thread;
    INVOKESTATIC org/mpisws/runtime/RuntimeEnvironment.waitRequest (Ljava/lang/Thread;)V
    ALOAD 1
    DUP
    DUP
    INVOKESTATIC java/lang/Thread.currentThread ()Ljava/lang/Thread;
    INVOKESTATIC org/mpisws/runtime/RuntimeEnvironment.exitMonitor (Ljava/lang/Object;Ljava/lang/Thread;)V
    MONITOREXIT
   L5
    GOTO L14
   L6
   FRAME FULL [org/mpisws/concurrent/programs/wrong/counter/BuggyCounter org/mpisws/concurrent/programs/wrong/counter/Counter] [java/lang/Throwable]
    ASTORE 4
    ALOAD 1
    DUP
    DUP
    INVOKESTATIC java/lang/Thread.currentThread ()Ljava/lang/Thread;
    INVOKESTATIC org/mpisws/runtime/RuntimeEnvironment.exitMonitor (Ljava/lang/Object;Ljava/lang/Thread;)V
    MONITOREXIT
   L7
    ALOAD 4
    ATHROW
   L14
    LINENUMBER 23 L14
   FRAME FULL [org/mpisws/concurrent/programs/wrong/counter/BuggyCounter org/mpisws/concurrent/programs/wrong/counter/Counter org/mpisws/concurrent/programs/wrong/counter/Counter] [org/mpisws/concurrent/programs/wrong/counter/Counter]
    INVOKESTATIC java/lang/Thread.currentThread ()Ljava/lang/Thread;
    INVOKESTATIC org/mpisws/runtime/RuntimeEnvironment.releasedLock (Ljava/lang/Object;Ljava/lang/Thread;)V
    INVOKESTATIC java/lang/Thread.currentThread ()Ljava/lang/Thread;
    INVOKESTATIC org/mpisws/runtime/RuntimeEnvironment.waitRequest (Ljava/lang/Thread;)V
    INVOKESTATIC java/lang/Thread.currentThread ()Ljava/lang/Thread;
    INVOKESTATIC org/mpisws/runtime/RuntimeEnvironment.finishThreadRequest (Ljava/lang/Thread;)V
    RETURN
    MAXSTACK = 8
    MAXLOCALS = 5

  // access flags 0x9
  public static main([Ljava/lang/String;)V throws java/lang/InterruptedException 
    INVOKESTATIC java/lang/Thread.currentThread ()Ljava/lang/Thread;
    INVOKESTATIC org/mpisws/runtime/RuntimeEnvironment.init (Ljava/lang/Thread;)V
    NEW org/mpisws/runtime/SchedulerThread
    DUP
    INVOKESPECIAL org/mpisws/runtime/SchedulerThread.<init> ()V
    ASTORE 5
    ALOAD 5
    LDC "SchedulerThread"
    INVOKEVIRTUAL org/mpisws/runtime/SchedulerThread.setName (Ljava/lang/String;)V
    INVOKESTATIC java/lang/Thread.currentThread ()Ljava/lang/Thread;
    ALOAD 5
    INVOKESTATIC org/mpisws/runtime/RuntimeEnvironment.initSchedulerThread (Ljava/lang/Thread;Ljava/lang/Thread;)V
   L0
    LINENUMBER 25 L0
    NEW org/mpisws/concurrent/programs/wrong/counter/Counter
    DUP
    INVOKESPECIAL org/mpisws/concurrent/programs/wrong/counter/Counter.<init> ()V
    ASTORE 1
   L1
    LINENUMBER 26 L1
    NEW org/mpisws/concurrent/programs/wrong/counter/Counter
    DUP
    INVOKESPECIAL org/mpisws/concurrent/programs/wrong/counter/Counter.<init> ()V
    ASTORE 2
   L2
    LINENUMBER 27 L2
    NEW org/mpisws/concurrent/programs/wrong/counter/BuggyCounter
    DUP
    DUP
    ALOAD 1
    ALOAD 2
    INVOKESPECIAL org/mpisws/concurrent/programs/wrong/counter/BuggyCounter.<init> (Lorg/mpisws/concurrent/programs/wrong/counter/Counter;Lorg/mpisws/concurrent/programs/wrong/counter/Counter;)V
    INVOKESTATIC org/mpisws/runtime/RuntimeEnvironment.addThread (Ljava/lang/Thread;)V
    ASTORE 3
   L3
    LINENUMBER 28 L3
    NEW org/mpisws/concurrent/programs/wrong/counter/BuggyCounter
    DUP
    DUP
    ALOAD 2
    ALOAD 1
    INVOKESPECIAL org/mpisws/concurrent/programs/wrong/counter/BuggyCounter.<init> (Lorg/mpisws/concurrent/programs/wrong/counter/Counter;Lorg/mpisws/concurrent/programs/wrong/counter/Counter;)V
    INVOKESTATIC org/mpisws/runtime/RuntimeEnvironment.addThread (Ljava/lang/Thread;)V
    ASTORE 4
   L4
    LINENUMBER 29 L4
    ALOAD 3
    INVOKESTATIC java/lang/Thread.currentThread ()Ljava/lang/Thread;
    INVOKESTATIC org/mpisws/runtime/RuntimeEnvironment.threadStart (Ljava/lang/Thread;Ljava/lang/Thread;)V
   L5
    LINENUMBER 30 L5
    ALOAD 4
    INVOKESTATIC java/lang/Thread.currentThread ()Ljava/lang/Thread;
    INVOKESTATIC org/mpisws/runtime/RuntimeEnvironment.threadStart (Ljava/lang/Thread;Ljava/lang/Thread;)V
   L6
    LINENUMBER 31 L6
    ALOAD 3
    DUP
    INVOKESTATIC java/lang/Thread.currentThread ()Ljava/lang/Thread;
    INVOKESTATIC org/mpisws/runtime/RuntimeEnvironment.threadJoin (Ljava/lang/Thread;Ljava/lang/Thread;)V
    INVOKEVIRTUAL org/mpisws/concurrent/programs/wrong/counter/BuggyCounter.join ()V
    INVOKESTATIC java/lang/Thread.currentThread ()Ljava/lang/Thread;
    INVOKESTATIC org/mpisws/runtime/RuntimeEnvironment.waitRequest (Ljava/lang/Thread;)V
   L7
    LINENUMBER 32 L7
    ALOAD 4
    DUP
    INVOKESTATIC java/lang/Thread.currentThread ()Ljava/lang/Thread;
    INVOKESTATIC org/mpisws/runtime/RuntimeEnvironment.threadJoin (Ljava/lang/Thread;Ljava/lang/Thread;)V
    INVOKEVIRTUAL org/mpisws/concurrent/programs/wrong/counter/BuggyCounter.join ()V
    INVOKESTATIC java/lang/Thread.currentThread ()Ljava/lang/Thread;
    INVOKESTATIC org/mpisws/runtime/RuntimeEnvironment.waitRequest (Ljava/lang/Thread;)V
   L8
    LINENUMBER 33 L8
    GETSTATIC java/lang/System.out : Ljava/io/PrintStream;
    INVOKESTATIC java/lang/Thread.currentThread ()Ljava/lang/Thread;
    INVOKEVIRTUAL java/lang/Thread.getName ()Ljava/lang/String;
    ALOAD 1
    DUP
    INVOKESTATIC java/lang/Thread.currentThread ()Ljava/lang/Thread;
    LDC "org.mpisws.concurrent.programs.wrong.counter.Counter"
    LDC "count"
    LDC "I"
    INVOKESTATIC org/mpisws/runtime/RuntimeEnvironment.readOperation (Ljava/lang/Object;Ljava/lang/Thread;Ljava/lang/String;Ljava/lang/String;Ljava/lang/String;)V
    GETFIELD org/mpisws/concurrent/programs/wrong/counter/Counter.count : I
    INVOKESTATIC java/lang/Thread.currentThread ()Ljava/lang/Thread;
    INVOKESTATIC org/mpisws/runtime/RuntimeEnvironment.waitRequest (Ljava/lang/Thread;)V
    NOP
    ALOAD 2
    DUP
    INVOKESTATIC java/lang/Thread.currentThread ()Ljava/lang/Thread;
    LDC "org.mpisws.concurrent.programs.wrong.counter.Counter"
    LDC "count"
    LDC "I"
    INVOKESTATIC org/mpisws/runtime/RuntimeEnvironment.readOperation (Ljava/lang/Object;Ljava/lang/Thread;Ljava/lang/String;Ljava/lang/String;Ljava/lang/String;)V
    GETFIELD org/mpisws/concurrent/programs/wrong/counter/Counter.count : I
    INVOKESTATIC java/lang/Thread.currentThread ()Ljava/lang/Thread;
    INVOKESTATIC org/mpisws/runtime/RuntimeEnvironment.waitRequest (Ljava/lang/Thread;)V
    NOP
    INVOKEDYNAMIC makeConcatWithConstants(Ljava/lang/String;II)Ljava/lang/String; [
      // handle kind 0x6 : INVOKESTATIC
      java/lang/invoke/StringConcatFactory.makeConcatWithConstants(Ljava/lang/invoke/MethodHandles$Lookup;Ljava/lang/String;Ljava/lang/invoke/MethodType;Ljava/lang/String;[Ljava/lang/Object;)Ljava/lang/invoke/CallSite;
      // arguments:
      "[\u0001 message] : The counter1 value is \u0001 and the counter2 value is \u0001"
    ]
    INVOKEVIRTUAL java/io/PrintStream.println (Ljava/lang/String;)V
   L9
    LINENUMBER 34 L9
    INVOKESTATIC java/lang/Thread.currentThread ()Ljava/lang/Thread;
    INVOKESTATIC org/mpisws/runtime/RuntimeEnvironment.finishThreadRequest (Ljava/lang/Thread;)V
    RETURN
    MAXSTACK = 9
    MAXLOCALS = 6
}
