// class version 61.0 (61)
// access flags 0x21
public class org/example/concurrent/programs/simple/counter/SimpleCounter extends java/lang/Thread {

  // compiled from: SimpleCounter.java
  // access flags 0x19
  public final static INNERCLASS java/lang/invoke/MethodHandles$Lookup java/lang/invoke/MethodHandles Lookup

  // access flags 0x2
  private I count

  // access flags 0x1
  public <init>(I)V
   L0
    LINENUMBER 5 L0
    ALOAD 0
    INVOKESPECIAL java/lang/Thread.<init> ()V
   L1
    LINENUMBER 6 L1
    ALOAD 0
    ILOAD 1
    DUP2
    INVOKESTATIC java/lang/Integer.valueOf (I)Ljava/lang/Integer;
    INVOKESTATIC java/lang/Thread.currentThread ()Ljava/lang/Thread;
    LDC "org.example.concurrent.programs.simple.counter.SimpleCounter"
    LDC "count"
    LDC "I"
    INVOKESTATIC org/example/runtime/RuntimeEnvironment.WriteOperation (Ljava/lang/Object;Ljava/lang/Object;Ljava/lang/Thread;Ljava/lang/String;Ljava/lang/String;Ljava/lang/String;)V
    PUTFIELD org/example/concurrent/programs/simple/counter/SimpleCounter.count : I
   L2
    LINENUMBER 7 L2
    RETURN
    MAXSTACK = 8
    MAXLOCALS = 2

  // access flags 0x1
  public run()V
    INVOKESTATIC java/lang/Thread.currentThread ()Ljava/lang/Thread;
    INVOKESTATIC org/example/runtime/RuntimeEnvironment.waitRequest (Ljava/lang/Thread;)V
   L0
    LINENUMBER 10 L0
    ALOAD 0
    ALOAD 0
    DUP
    INVOKESTATIC java/lang/Thread.currentThread ()Ljava/lang/Thread;
    LDC "org.example.concurrent.programs.simple.counter.SimpleCounter"
    LDC "count"
    LDC "I"
    INVOKESTATIC org/example/runtime/RuntimeEnvironment.ReadOperation (Ljava/lang/Object;Ljava/lang/Thread;Ljava/lang/String;Ljava/lang/String;Ljava/lang/String;)V
    GETFIELD org/example/concurrent/programs/simple/counter/SimpleCounter.count : I
    ICONST_1
    IADD
    DUP2
    INVOKESTATIC java/lang/Integer.valueOf (I)Ljava/lang/Integer;
    INVOKESTATIC java/lang/Thread.currentThread ()Ljava/lang/Thread;
    LDC "org.example.concurrent.programs.simple.counter.SimpleCounter"
    LDC "count"
    LDC "I"
    INVOKESTATIC org/example/runtime/RuntimeEnvironment.WriteOperation (Ljava/lang/Object;Ljava/lang/Object;Ljava/lang/Thread;Ljava/lang/String;Ljava/lang/String;Ljava/lang/String;)V
    PUTFIELD org/example/concurrent/programs/simple/counter/SimpleCounter.count : I
   L1
    LINENUMBER 11 L1
    GETSTATIC java/lang/System.out : Ljava/io/PrintStream;
    ALOAD 0
    INVOKEVIRTUAL org/example/concurrent/programs/simple/counter/SimpleCounter.getName ()Ljava/lang/String;
    ALOAD 0
    DUP
    INVOKESTATIC java/lang/Thread.currentThread ()Ljava/lang/Thread;
    LDC "org.example.concurrent.programs.simple.counter.SimpleCounter"
    LDC "count"
    LDC "I"
    INVOKESTATIC org/example/runtime/RuntimeEnvironment.ReadOperation (Ljava/lang/Object;Ljava/lang/Thread;Ljava/lang/String;Ljava/lang/String;Ljava/lang/String;)V
    GETFIELD org/example/concurrent/programs/simple/counter/SimpleCounter.count : I
    INVOKEDYNAMIC makeConcatWithConstants(Ljava/lang/String;I)Ljava/lang/String; [
      // handle kind 0x6 : INVOKESTATIC
      java/lang/invoke/StringConcatFactory.makeConcatWithConstants(Ljava/lang/invoke/MethodHandles$Lookup;Ljava/lang/String;Ljava/lang/invoke/MethodType;Ljava/lang/String;[Ljava/lang/Object;)Ljava/lang/invoke/CallSite;
      // arguments:
      "[\u0001 message] : The counter value is \u0001"
    ]
    INVOKEVIRTUAL java/io/PrintStream.println (Ljava/lang/String;)V
   L2
    LINENUMBER 12 L2
    INVOKESTATIC java/lang/Thread.currentThread ()Ljava/lang/Thread;
    INVOKESTATIC org/example/runtime/RuntimeEnvironment.finishThreadRequest (Ljava/lang/Thread;)V
    RETURN
    MAXSTACK = 8
    MAXLOCALS = 1

  // access flags 0x9
  public static main([Ljava/lang/String;)V
    TRYCATCHBLOCK L0 L1 L2 null
    TRYCATCHBLOCK L2 L3 L2 null
    TRYCATCHBLOCK L4 L5 L6 null
    TRYCATCHBLOCK L6 L7 L6 null
    TRYCATCHBLOCK L8 L9 L10 null
    TRYCATCHBLOCK L10 L11 L10 null
    TRYCATCHBLOCK L12 L13 L14 null
    TRYCATCHBLOCK L14 L15 L14 null
    TRYCATCHBLOCK L16 L17 L18 null
    TRYCATCHBLOCK L18 L19 L18 null
    INVOKESTATIC java/lang/Thread.currentThread ()Ljava/lang/Thread;
    INVOKESTATIC org/example/runtime/RuntimeEnvironment.init (Ljava/lang/Thread;)V
    NEW org/example/runtime/SchedulerThread
    DUP
    INVOKESPECIAL org/example/runtime/SchedulerThread.<init> ()V
    ASTORE 14
    ALOAD 14
    LDC "SchedulerThread"
    INVOKEVIRTUAL org/example/runtime/SchedulerThread.setName (Ljava/lang/String;)V
    INVOKESTATIC java/lang/Thread.currentThread ()Ljava/lang/Thread;
    ALOAD 14
    INVOKESTATIC org/example/runtime/RuntimeEnvironment.initSchedulerThread (Ljava/lang/Thread;Ljava/lang/Thread;)V
   L20
    LINENUMBER 15 L20
    NEW java/lang/Object
    DUP
    INVOKESPECIAL java/lang/Object.<init> ()V
    ASTORE 1
   L21
    LINENUMBER 16 L21
    NEW java/lang/Object
    DUP
    INVOKESPECIAL java/lang/Object.<init> ()V
    ASTORE 2
   L22
    LINENUMBER 17 L22
    NEW java/lang/Object
    DUP
    INVOKESPECIAL java/lang/Object.<init> ()V
    ASTORE 3
   L23
    LINENUMBER 18 L23
    NEW java/lang/Object
    DUP
    INVOKESPECIAL java/lang/Object.<init> ()V
    ASTORE 4
   L24
    LINENUMBER 19 L24
    NEW org/example/concurrent/programs/simple/counter/SimpleCounter
    DUP
    ICONST_0
    INVOKESPECIAL org/example/concurrent/programs/simple/counter/SimpleCounter.<init> (I)V
    ASTORE 5
    ALOAD 5
    INVOKESTATIC org/example/runtime/RuntimeEnvironment.addThread (Ljava/lang/Thread;)V
   L25
    LINENUMBER 20 L25
    NEW org/example/concurrent/programs/simple/counter/SimpleCounter
    DUP
    ICONST_0
    INVOKESPECIAL org/example/concurrent/programs/simple/counter/SimpleCounter.<init> (I)V
    ASTORE 6
    ALOAD 6
    INVOKESTATIC org/example/runtime/RuntimeEnvironment.addThread (Ljava/lang/Thread;)V
   L26
    LINENUMBER 21 L26
    ALOAD 5
    INVOKESTATIC java/lang/Thread.currentThread ()Ljava/lang/Thread;
    ALOAD 5
    INVOKESTATIC org/example/runtime/RuntimeEnvironment.threadStart (Ljava/lang/Thread;Ljava/lang/Thread;)V
   L27
    LINENUMBER 22 L27
    ALOAD 6
    INVOKESTATIC java/lang/Thread.currentThread ()Ljava/lang/Thread;
    ALOAD 6
    INVOKESTATIC org/example/runtime/RuntimeEnvironment.threadStart (Ljava/lang/Thread;Ljava/lang/Thread;)V
   L28
    LINENUMBER 23 L28
    ALOAD 1
    DUP
    ASTORE 7
    ALOAD 7
    INVOKESTATIC java/lang/Thread.currentThread ()Ljava/lang/Thread;
    INVOKESTATIC org/example/runtime/RuntimeEnvironment.enterMonitor (Ljava/lang/Object;Ljava/lang/Thread;)V
    MONITORENTER
   L12
    LINENUMBER 24 L12
    ALOAD 7
    INVOKESTATIC java/lang/Thread.currentThread ()Ljava/lang/Thread;
    INVOKESTATIC org/example/runtime/RuntimeEnvironment.acquiredLock (Ljava/lang/Object;Ljava/lang/Thread;)V
    ALOAD 2
    DUP
    ASTORE 8
    ALOAD 8
    INVOKESTATIC java/lang/Thread.currentThread ()Ljava/lang/Thread;
    INVOKESTATIC org/example/runtime/RuntimeEnvironment.enterMonitor (Ljava/lang/Object;Ljava/lang/Thread;)V
    MONITORENTER
   L0
    LINENUMBER 25 L0
    ALOAD 8
    INVOKESTATIC java/lang/Thread.currentThread ()Ljava/lang/Thread;
    INVOKESTATIC org/example/runtime/RuntimeEnvironment.acquiredLock (Ljava/lang/Object;Ljava/lang/Thread;)V
    GETSTATIC java/lang/System.out : Ljava/io/PrintStream;
    INVOKESTATIC java/lang/Thread.currentThread ()Ljava/lang/Thread;
    INVOKEVIRTUAL java/lang/Thread.getName ()Ljava/lang/String;
    INVOKEDYNAMIC makeConcatWithConstants(Ljava/lang/String;)Ljava/lang/String; [
      // handle kind 0x6 : INVOKESTATIC
      java/lang/invoke/StringConcatFactory.makeConcatWithConstants(Ljava/lang/invoke/MethodHandles$Lookup;Ljava/lang/String;Ljava/lang/invoke/MethodType;Ljava/lang/String;[Ljava/lang/Object;)Ljava/lang/invoke/CallSite;
      // arguments:
      "[\u0001 message] : Entered the synchronized block"
    ]
    INVOKEVIRTUAL java/io/PrintStream.println (Ljava/lang/String;)V
   L29
    LINENUMBER 26 L29
    ALOAD 8
    ALOAD 8
    INVOKESTATIC java/lang/Thread.currentThread ()Ljava/lang/Thread;
    INVOKESTATIC org/example/runtime/RuntimeEnvironment.exitMonitor (Ljava/lang/Object;Ljava/lang/Thread;)V
    MONITOREXIT
   L1
    GOTO L30
   L2
   FRAME FULL [[Ljava/lang/String; java/lang/Object java/lang/Object java/lang/Object java/lang/Object org/example/concurrent/programs/simple/counter/SimpleCounter org/example/concurrent/programs/simple/counter/SimpleCounter java/lang/Object java/lang/Object] [java/lang/Throwable]
    ASTORE 9
    ALOAD 8
    ALOAD 8
    INVOKESTATIC java/lang/Thread.currentThread ()Ljava/lang/Thread;
    INVOKESTATIC org/example/runtime/RuntimeEnvironment.exitMonitor (Ljava/lang/Object;Ljava/lang/Thread;)V
    MONITOREXIT
   L3
    ALOAD 9
    ATHROW
   L30
    LINENUMBER 27 L30
   FRAME FULL [[Ljava/lang/String; java/lang/Object java/lang/Object java/lang/Object java/lang/Object org/example/concurrent/programs/simple/counter/SimpleCounter org/example/concurrent/programs/simple/counter/SimpleCounter java/lang/Object java/lang/Object] [org/example/concurrent/programs/simple/counter/SimpleCounter org/example/concurrent/programs/simple/counter/SimpleCounter]
    ALOAD 8
    INVOKESTATIC java/lang/Thread.currentThread ()Ljava/lang/Thread;
    INVOKESTATIC org/example/runtime/RuntimeEnvironment.releasedLock (Ljava/lang/Object;Ljava/lang/Thread;)V
    GETSTATIC java/lang/System.out : Ljava/io/PrintStream;
    INVOKESTATIC java/lang/Thread.currentThread ()Ljava/lang/Thread;
    INVOKEVIRTUAL java/lang/Thread.getName ()Ljava/lang/String;
    INVOKEDYNAMIC makeConcatWithConstants(Ljava/lang/String;)Ljava/lang/String; [
      // handle kind 0x6 : INVOKESTATIC
      java/lang/invoke/StringConcatFactory.makeConcatWithConstants(Ljava/lang/invoke/MethodHandles$Lookup;Ljava/lang/String;Ljava/lang/invoke/MethodType;Ljava/lang/String;[Ljava/lang/Object;)Ljava/lang/invoke/CallSite;
      // arguments:
      "[\u0001 message] : Entered the synchronized block"
    ]
    INVOKEVIRTUAL java/io/PrintStream.println (Ljava/lang/String;)V
   L31
    LINENUMBER 28 L31
    ALOAD 3
    DUP
    ASTORE 8
    ALOAD 8
    INVOKESTATIC java/lang/Thread.currentThread ()Ljava/lang/Thread;
    INVOKESTATIC org/example/runtime/RuntimeEnvironment.enterMonitor (Ljava/lang/Object;Ljava/lang/Thread;)V
    MONITORENTER
   L8
    LINENUMBER 29 L8
    ALOAD 8
    INVOKESTATIC java/lang/Thread.currentThread ()Ljava/lang/Thread;
    INVOKESTATIC org/example/runtime/RuntimeEnvironment.acquiredLock (Ljava/lang/Object;Ljava/lang/Thread;)V
    ALOAD 4
    DUP
    ASTORE 9
    ALOAD 9
    INVOKESTATIC java/lang/Thread.currentThread ()Ljava/lang/Thread;
    INVOKESTATIC org/example/runtime/RuntimeEnvironment.enterMonitor (Ljava/lang/Object;Ljava/lang/Thread;)V
    MONITORENTER
   L4
    LINENUMBER 30 L4
    ALOAD 9
    INVOKESTATIC java/lang/Thread.currentThread ()Ljava/lang/Thread;
    INVOKESTATIC org/example/runtime/RuntimeEnvironment.acquiredLock (Ljava/lang/Object;Ljava/lang/Thread;)V
    GETSTATIC java/lang/System.out : Ljava/io/PrintStream;
    INVOKESTATIC java/lang/Thread.currentThread ()Ljava/lang/Thread;
    INVOKEVIRTUAL java/lang/Thread.getName ()Ljava/lang/String;
    INVOKEDYNAMIC makeConcatWithConstants(Ljava/lang/String;)Ljava/lang/String; [
      // handle kind 0x6 : INVOKESTATIC
      java/lang/invoke/StringConcatFactory.makeConcatWithConstants(Ljava/lang/invoke/MethodHandles$Lookup;Ljava/lang/String;Ljava/lang/invoke/MethodType;Ljava/lang/String;[Ljava/lang/Object;)Ljava/lang/invoke/CallSite;
      // arguments:
      "[\u0001 message] : Entered the synchronized block"
    ]
    INVOKEVIRTUAL java/io/PrintStream.println (Ljava/lang/String;)V
   L32
    LINENUMBER 31 L32
    ALOAD 9
    ALOAD 9
    INVOKESTATIC java/lang/Thread.currentThread ()Ljava/lang/Thread;
    INVOKESTATIC org/example/runtime/RuntimeEnvironment.exitMonitor (Ljava/lang/Object;Ljava/lang/Thread;)V
    MONITOREXIT
   L5
    GOTO L33
   L6
   FRAME FULL [[Ljava/lang/String; java/lang/Object java/lang/Object java/lang/Object java/lang/Object org/example/concurrent/programs/simple/counter/SimpleCounter org/example/concurrent/programs/simple/counter/SimpleCounter java/lang/Object java/lang/Object java/lang/Object] [java/lang/Throwable]
    ASTORE 10
    ALOAD 9
    ALOAD 9
    INVOKESTATIC java/lang/Thread.currentThread ()Ljava/lang/Thread;
    INVOKESTATIC org/example/runtime/RuntimeEnvironment.exitMonitor (Ljava/lang/Object;Ljava/lang/Thread;)V
    MONITOREXIT
   L7
    ALOAD 10
    ATHROW
   L33
    LINENUMBER 32 L33
   FRAME FULL [[Ljava/lang/String; java/lang/Object java/lang/Object java/lang/Object java/lang/Object org/example/concurrent/programs/simple/counter/SimpleCounter org/example/concurrent/programs/simple/counter/SimpleCounter java/lang/Object java/lang/Object java/lang/Object] [org/example/concurrent/programs/simple/counter/SimpleCounter org/example/concurrent/programs/simple/counter/SimpleCounter]
    ALOAD 9
    INVOKESTATIC java/lang/Thread.currentThread ()Ljava/lang/Thread;
    INVOKESTATIC org/example/runtime/RuntimeEnvironment.releasedLock (Ljava/lang/Object;Ljava/lang/Thread;)V
    GETSTATIC java/lang/System.out : Ljava/io/PrintStream;
    INVOKESTATIC java/lang/Thread.currentThread ()Ljava/lang/Thread;
    INVOKEVIRTUAL java/lang/Thread.getName ()Ljava/lang/String;
    INVOKEDYNAMIC makeConcatWithConstants(Ljava/lang/String;)Ljava/lang/String; [
      // handle kind 0x6 : INVOKESTATIC
      java/lang/invoke/StringConcatFactory.makeConcatWithConstants(Ljava/lang/invoke/MethodHandles$Lookup;Ljava/lang/String;Ljava/lang/invoke/MethodType;Ljava/lang/String;[Ljava/lang/Object;)Ljava/lang/invoke/CallSite;
      // arguments:
      "[\u0001 message] : Entered the synchronized block"
    ]
    INVOKEVIRTUAL java/io/PrintStream.println (Ljava/lang/String;)V
   L34
    LINENUMBER 33 L34
    ALOAD 8
    ALOAD 8
    INVOKESTATIC java/lang/Thread.currentThread ()Ljava/lang/Thread;
    INVOKESTATIC org/example/runtime/RuntimeEnvironment.exitMonitor (Ljava/lang/Object;Ljava/lang/Thread;)V
    MONITOREXIT
   L9
    GOTO L35
   L10
   FRAME FULL [[Ljava/lang/String; java/lang/Object java/lang/Object java/lang/Object java/lang/Object org/example/concurrent/programs/simple/counter/SimpleCounter org/example/concurrent/programs/simple/counter/SimpleCounter java/lang/Object java/lang/Object] [java/lang/Throwable]
    ASTORE 11
    ALOAD 8
    ALOAD 8
    INVOKESTATIC java/lang/Thread.currentThread ()Ljava/lang/Thread;
    INVOKESTATIC org/example/runtime/RuntimeEnvironment.exitMonitor (Ljava/lang/Object;Ljava/lang/Thread;)V
    MONITOREXIT
   L11
    ALOAD 11
    ATHROW
   L35
    LINENUMBER 34 L35
   FRAME FULL [[Ljava/lang/String; java/lang/Object java/lang/Object java/lang/Object java/lang/Object org/example/concurrent/programs/simple/counter/SimpleCounter org/example/concurrent/programs/simple/counter/SimpleCounter java/lang/Object java/lang/Object java/lang/Object] [org/example/concurrent/programs/simple/counter/SimpleCounter org/example/concurrent/programs/simple/counter/SimpleCounter]
    ALOAD 8
    INVOKESTATIC java/lang/Thread.currentThread ()Ljava/lang/Thread;
    INVOKESTATIC org/example/runtime/RuntimeEnvironment.releasedLock (Ljava/lang/Object;Ljava/lang/Thread;)V
    ALOAD 7
    ALOAD 7
    INVOKESTATIC java/lang/Thread.currentThread ()Ljava/lang/Thread;
    INVOKESTATIC org/example/runtime/RuntimeEnvironment.exitMonitor (Ljava/lang/Object;Ljava/lang/Thread;)V
    MONITOREXIT
   L13
    GOTO L36
   L14
   FRAME FULL [[Ljava/lang/String; java/lang/Object java/lang/Object java/lang/Object java/lang/Object org/example/concurrent/programs/simple/counter/SimpleCounter org/example/concurrent/programs/simple/counter/SimpleCounter java/lang/Object] [java/lang/Throwable]
    ASTORE 12
    ALOAD 7
    ALOAD 7
    INVOKESTATIC java/lang/Thread.currentThread ()Ljava/lang/Thread;
    INVOKESTATIC org/example/runtime/RuntimeEnvironment.exitMonitor (Ljava/lang/Object;Ljava/lang/Thread;)V
    MONITOREXIT
   L15
    ALOAD 12
    ATHROW
   L36
    LINENUMBER 35 L36
   FRAME FULL [[Ljava/lang/String; java/lang/Object java/lang/Object java/lang/Object java/lang/Object org/example/concurrent/programs/simple/counter/SimpleCounter org/example/concurrent/programs/simple/counter/SimpleCounter java/lang/Object java/lang/Object java/lang/Object] [org/example/concurrent/programs/simple/counter/SimpleCounter org/example/concurrent/programs/simple/counter/SimpleCounter]
    ALOAD 7
    INVOKESTATIC java/lang/Thread.currentThread ()Ljava/lang/Thread;
    INVOKESTATIC org/example/runtime/RuntimeEnvironment.releasedLock (Ljava/lang/Object;Ljava/lang/Thread;)V
    ALOAD 2
    DUP
    ASTORE 7
    ALOAD 7
    INVOKESTATIC java/lang/Thread.currentThread ()Ljava/lang/Thread;
    INVOKESTATIC org/example/runtime/RuntimeEnvironment.enterMonitor (Ljava/lang/Object;Ljava/lang/Thread;)V
    MONITORENTER
   L16
    LINENUMBER 36 L16
    ALOAD 7
    INVOKESTATIC java/lang/Thread.currentThread ()Ljava/lang/Thread;
    INVOKESTATIC org/example/runtime/RuntimeEnvironment.acquiredLock (Ljava/lang/Object;Ljava/lang/Thread;)V
    GETSTATIC java/lang/System.out : Ljava/io/PrintStream;
    INVOKESTATIC java/lang/Thread.currentThread ()Ljava/lang/Thread;
    INVOKEVIRTUAL java/lang/Thread.getName ()Ljava/lang/String;
    INVOKEDYNAMIC makeConcatWithConstants(Ljava/lang/String;)Ljava/lang/String; [
      // handle kind 0x6 : INVOKESTATIC
      java/lang/invoke/StringConcatFactory.makeConcatWithConstants(Ljava/lang/invoke/MethodHandles$Lookup;Ljava/lang/String;Ljava/lang/invoke/MethodType;Ljava/lang/String;[Ljava/lang/Object;)Ljava/lang/invoke/CallSite;
      // arguments:
      "[\u0001 message] : Entered the synchronized block"
    ]
    INVOKEVIRTUAL java/io/PrintStream.println (Ljava/lang/String;)V
   L37
    LINENUMBER 37 L37
    ALOAD 7
    ALOAD 7
    INVOKESTATIC java/lang/Thread.currentThread ()Ljava/lang/Thread;
    INVOKESTATIC org/example/runtime/RuntimeEnvironment.exitMonitor (Ljava/lang/Object;Ljava/lang/Thread;)V
    MONITOREXIT
   L17
    GOTO L38
   L18
   FRAME SAME1 java/lang/Throwable
    ASTORE 13
    ALOAD 7
    ALOAD 7
    INVOKESTATIC java/lang/Thread.currentThread ()Ljava/lang/Thread;
    INVOKESTATIC org/example/runtime/RuntimeEnvironment.exitMonitor (Ljava/lang/Object;Ljava/lang/Thread;)V
    MONITOREXIT
   L19
    ALOAD 13
    ATHROW
   L38
    LINENUMBER 38 L38
   FRAME FULL [[Ljava/lang/String; java/lang/Object java/lang/Object java/lang/Object java/lang/Object org/example/concurrent/programs/simple/counter/SimpleCounter org/example/concurrent/programs/simple/counter/SimpleCounter java/lang/Object java/lang/Object java/lang/Object] [org/example/concurrent/programs/simple/counter/SimpleCounter org/example/concurrent/programs/simple/counter/SimpleCounter]
    ALOAD 7
    INVOKESTATIC java/lang/Thread.currentThread ()Ljava/lang/Thread;
    INVOKESTATIC org/example/runtime/RuntimeEnvironment.releasedLock (Ljava/lang/Object;Ljava/lang/Thread;)V
    INVOKESTATIC java/lang/Thread.currentThread ()Ljava/lang/Thread;
    INVOKESTATIC org/example/runtime/RuntimeEnvironment.finishThreadRequest (Ljava/lang/Thread;)V
    RETURN
    MAXSTACK = 5
    MAXLOCALS = 15
}
