// class version 61.0 (61)
// access flags 0x21
public class org/mpisws/concurrent/programs/simple/message/SimpleMessage {

  // compiled from: SimpleMessage.java

  // access flags 0x1
  public <init>()V
   L0
    LINENUMBER 3 L0
    ALOAD 0
    INVOKESPECIAL java/lang/Object.<init> ()V
    RETURN
    MAXSTACK = 1
    MAXLOCALS = 1

  // access flags 0x9
  public static main([Ljava/lang/String;)V
    INVOKESTATIC java/lang/Thread.currentThread ()Ljava/lang/Thread;
    INVOKESTATIC org/mpisws/runtime/RuntimeEnvironment.init (Ljava/lang/Thread;)V
    NEW org/mpisws/runtime/SchedulerThread
    DUP
    INVOKESPECIAL org/mpisws/runtime/SchedulerThread.<init> ()V
    ASTORE 3
    ALOAD 3
    LDC "SchedulerThread"
    INVOKEVIRTUAL org/mpisws/runtime/SchedulerThread.setName (Ljava/lang/String;)V
    INVOKESTATIC java/lang/Thread.currentThread ()Ljava/lang/Thread;
    ALOAD 3
    INVOKESTATIC org/mpisws/runtime/RuntimeEnvironment.initSchedulerThread (Ljava/lang/Thread;Ljava/lang/Thread;)V
    INVOKESTATIC java/lang/Thread.currentThread ()Ljava/lang/Thread;
    INVOKESTATIC org/mpisws/runtime/RuntimeEnvironment.mainThreadStart (Ljava/lang/Thread;)V
   L0
    LINENUMBER 6 L0
    NEW org/mpisws/concurrent/programs/simple/message/SenderThread
    DUP
    INVOKESPECIAL org/mpisws/concurrent/programs/simple/message/SenderThread.<init> ()V
    ASTORE 1
   L1
    LINENUMBER 7 L1
    NEW org/mpisws/concurrent/programs/simple/message/ReceiverThread
    DUP
    INVOKESPECIAL org/mpisws/concurrent/programs/simple/message/ReceiverThread.<init> ()V
    ASTORE 2
   L2
    LINENUMBER 9 L2
    ALOAD 1
    ALOAD 2
    INVOKEVIRTUAL org/mpisws/concurrent/programs/simple/message/ReceiverThread.getId ()J
    PUTFIELD org/mpisws/concurrent/programs/simple/message/SenderThread.receiver_tid : J
   L3
    LINENUMBER 11 L3
    ALOAD 1
    INVOKESTATIC java/lang/Thread.currentThread ()Ljava/lang/Thread;
    INVOKESTATIC org/mpisws/runtime/RuntimeEnvironment.threadStart (Ljava/lang/Thread;Ljava/lang/Thread;)V
   L4
    LINENUMBER 12 L4
    ALOAD 2
    INVOKESTATIC java/lang/Thread.currentThread ()Ljava/lang/Thread;
    INVOKESTATIC org/mpisws/runtime/RuntimeEnvironment.threadStart (Ljava/lang/Thread;Ljava/lang/Thread;)V
   L5
    LINENUMBER 14 L5
    ALOAD 1
    INVOKEVIRTUAL org/mpisws/concurrent/programs/simple/message/SenderThread.joinThread ()V
   L6
    LINENUMBER 15 L6
    ALOAD 2
    INVOKEVIRTUAL org/mpisws/concurrent/programs/simple/message/ReceiverThread.joinThread ()V
   L7
    LINENUMBER 17 L7
    GETSTATIC java/lang/System.out : Ljava/io/PrintStream;
    LDC "Simple Message finished"
    INVOKEVIRTUAL java/io/PrintStream.println (Ljava/lang/String;)V
   L8
    LINENUMBER 18 L8
    INVOKESTATIC java/lang/Thread.currentThread ()Ljava/lang/Thread;
    INVOKESTATIC org/mpisws/runtime/RuntimeEnvironment.finishThreadRequest (Ljava/lang/Thread;)V
    RETURN
    MAXSTACK = 3
    MAXLOCALS = 4
}
