// class version 61.0 (61)
// access flags 0x21
public class org/mpisws/concurrent/programs/simple/counter/SimpleCounter extends java/lang/Thread {

  // compiled from: SimpleCounter.java

  // access flags 0x2
  private Lorg/mpisws/concurrent/programs/simple/counter/Counter; counter

  // access flags 0x1018
  final static synthetic Z $assertionsDisabled

  // access flags 0x1
  public <init>(Lorg/mpisws/concurrent/programs/simple/counter/Counter;)V
   L0
    LINENUMBER 7 L0
    ALOAD 0
    INVOKESPECIAL java/lang/Thread.<init> ()V
   L1
    LINENUMBER 8 L1
    ALOAD 0
    ALOAD 1
    PUTFIELD org/mpisws/concurrent/programs/simple/counter/SimpleCounter.counter : Lorg/mpisws/concurrent/programs/simple/counter/Counter;
   L2
    LINENUMBER 9 L2
    RETURN
    MAXSTACK = 2
    MAXLOCALS = 2

  // access flags 0x1
  public run()V
    INVOKESTATIC java/lang/Thread.currentThread ()Ljava/lang/Thread;
    INVOKESTATIC org/mpisws/runtime/RuntimeEnvironment.waitRequest (Ljava/lang/Thread;)V
   L0
    LINENUMBER 12 L0
    ALOAD 0
    GETFIELD org/mpisws/concurrent/programs/simple/counter/SimpleCounter.counter : Lorg/mpisws/concurrent/programs/simple/counter/Counter;
    INVOKEVIRTUAL org/mpisws/concurrent/programs/simple/counter/Counter.increment ()V
   L1
    LINENUMBER 13 L1
    NEW org/mpisws/concurrent/programs/simple/counter/HelpingThread
    DUP
    DUP
    ALOAD 0
    GETFIELD org/mpisws/concurrent/programs/simple/counter/SimpleCounter.counter : Lorg/mpisws/concurrent/programs/simple/counter/Counter;
    INVOKESPECIAL org/mpisws/concurrent/programs/simple/counter/HelpingThread.<init> (Lorg/mpisws/concurrent/programs/simple/counter/Counter;)V
    INVOKESTATIC org/mpisws/runtime/RuntimeEnvironment.addThread (Ljava/lang/Thread;)V
    ASTORE 1
   L2
    LINENUMBER 14 L2
    ALOAD 1
    INVOKESTATIC java/lang/Thread.currentThread ()Ljava/lang/Thread;
    INVOKESTATIC org/mpisws/runtime/RuntimeEnvironment.threadStart (Ljava/lang/Thread;Ljava/lang/Thread;)V
   L3
    LINENUMBER 15 L3
    INVOKESTATIC java/lang/Thread.currentThread ()Ljava/lang/Thread;
    INVOKESTATIC org/mpisws/runtime/RuntimeEnvironment.finishThreadRequest (Ljava/lang/Thread;)V
    RETURN
    MAXSTACK = 4
    MAXLOCALS = 2

  // access flags 0x9
  public static main([Ljava/lang/String;)V
    TRYCATCHBLOCK L0 L1 L2 java/lang/InterruptedException
    INVOKESTATIC java/lang/Thread.currentThread ()Ljava/lang/Thread;
    INVOKESTATIC org/mpisws/runtime/RuntimeEnvironment.init (Ljava/lang/Thread;)V
    NEW org/mpisws/runtime/SchedulerThread
    DUP
    INVOKESPECIAL org/mpisws/runtime/SchedulerThread.<init> ()V
    ASTORE 5
    ALOAD 5
    LDC "SchedulerThread"
    INVOKEVIRTUAL org/mpisws/runtime/SchedulerThread.setName (Ljava/lang/String;)V
    INVOKESTATIC java/lang/Thread.currentThread ()Ljava/lang/Thread;
    ALOAD 5
    INVOKESTATIC org/mpisws/runtime/RuntimeEnvironment.initSchedulerThread (Ljava/lang/Thread;Ljava/lang/Thread;)V
   L3
    LINENUMBER 18 L3
    NEW org/mpisws/concurrent/programs/simple/counter/Counter
    DUP
    INVOKESPECIAL org/mpisws/concurrent/programs/simple/counter/Counter.<init> ()V
    ASTORE 1
   L4
    LINENUMBER 19 L4
    NEW org/mpisws/concurrent/programs/simple/counter/SimpleCounter
    DUP
    DUP
    ALOAD 1
    INVOKESPECIAL org/mpisws/concurrent/programs/simple/counter/SimpleCounter.<init> (Lorg/mpisws/concurrent/programs/simple/counter/Counter;)V
    INVOKESTATIC org/mpisws/runtime/RuntimeEnvironment.addThread (Ljava/lang/Thread;)V
    ASTORE 2
   L5
    LINENUMBER 20 L5
    NEW org/mpisws/concurrent/programs/simple/counter/SimpleCounter
    DUP
    DUP
    ALOAD 1
    INVOKESPECIAL org/mpisws/concurrent/programs/simple/counter/SimpleCounter.<init> (Lorg/mpisws/concurrent/programs/simple/counter/Counter;)V
    INVOKESTATIC org/mpisws/runtime/RuntimeEnvironment.addThread (Ljava/lang/Thread;)V
    ASTORE 3
   L6
    LINENUMBER 21 L6
    ALOAD 2
    INVOKESTATIC java/lang/Thread.currentThread ()Ljava/lang/Thread;
    INVOKESTATIC org/mpisws/runtime/RuntimeEnvironment.threadStart (Ljava/lang/Thread;Ljava/lang/Thread;)V
   L7
    LINENUMBER 22 L7
    ALOAD 3
    INVOKESTATIC java/lang/Thread.currentThread ()Ljava/lang/Thread;
    INVOKESTATIC org/mpisws/runtime/RuntimeEnvironment.threadStart (Ljava/lang/Thread;Ljava/lang/Thread;)V
   L0
    LINENUMBER 24 L0
    ALOAD 2
    DUP
    INVOKESTATIC java/lang/Thread.currentThread ()Ljava/lang/Thread;
    INVOKESTATIC org/mpisws/runtime/RuntimeEnvironment.threadJoin (Ljava/lang/Thread;Ljava/lang/Thread;)V
    INVOKEVIRTUAL org/mpisws/concurrent/programs/simple/counter/SimpleCounter.join ()V
    INVOKESTATIC java/lang/Thread.currentThread ()Ljava/lang/Thread;
    INVOKESTATIC org/mpisws/runtime/RuntimeEnvironment.waitRequest (Ljava/lang/Thread;)V
   L8
    LINENUMBER 25 L8
    ALOAD 3
    DUP
    INVOKESTATIC java/lang/Thread.currentThread ()Ljava/lang/Thread;
    INVOKESTATIC org/mpisws/runtime/RuntimeEnvironment.threadJoin (Ljava/lang/Thread;Ljava/lang/Thread;)V
    INVOKEVIRTUAL org/mpisws/concurrent/programs/simple/counter/SimpleCounter.join ()V
    INVOKESTATIC java/lang/Thread.currentThread ()Ljava/lang/Thread;
    INVOKESTATIC org/mpisws/runtime/RuntimeEnvironment.waitRequest (Ljava/lang/Thread;)V
   L1
    LINENUMBER 28 L1
    GOTO L9
   L2
    LINENUMBER 26 L2
   FRAME FULL [[Ljava/lang/String; org/mpisws/concurrent/programs/simple/counter/Counter org/mpisws/concurrent/programs/simple/counter/SimpleCounter org/mpisws/concurrent/programs/simple/counter/SimpleCounter T org/mpisws/runtime/SchedulerThread] [java/lang/InterruptedException]
    ASTORE 4
   L10
    LINENUMBER 27 L10
    ALOAD 4
    INVOKEVIRTUAL java/lang/InterruptedException.printStackTrace ()V
   L9
    LINENUMBER 29 L9
   FRAME SAME
    GETSTATIC org/mpisws/concurrent/programs/simple/counter/SimpleCounter.$assertionsDisabled : Z
    IFNE L11
    ALOAD 1
    INVOKEVIRTUAL org/mpisws/concurrent/programs/simple/counter/Counter.getValue ()I
    ICONST_4
    IF_ICMPEQ L11
    NEW java/lang/AssertionError
    DUP
    LDC "Counter value is not 4"
    INVOKESTATIC org/mpisws/runtime/RuntimeEnvironment.assertOperation (Ljava/lang/String;)V
    INVOKESTATIC java/lang/Thread.currentThread ()Ljava/lang/Thread;
    INVOKESTATIC org/mpisws/runtime/RuntimeEnvironment.finishThreadRequest (Ljava/lang/Thread;)V
    RETURN
   L11
    LINENUMBER 30 L11
   FRAME SAME
    GETSTATIC java/lang/System.out : Ljava/io/PrintStream;
    LDC "Counter value is 4"
    INVOKEVIRTUAL java/io/PrintStream.println (Ljava/lang/String;)V
   L12
    LINENUMBER 31 L12
    INVOKESTATIC java/lang/Thread.currentThread ()Ljava/lang/Thread;
    INVOKESTATIC org/mpisws/runtime/RuntimeEnvironment.finishThreadRequest (Ljava/lang/Thread;)V
    RETURN
    MAXSTACK = 4
    MAXLOCALS = 6

  // access flags 0x8
  static <clinit>()V
   L0
    LINENUMBER 3 L0
    LDC Lorg/mpisws/concurrent/programs/simple/counter/SimpleCounter;.class
    INVOKEVIRTUAL java/lang/Class.desiredAssertionStatus ()Z
    IFNE L1
    ICONST_1
    GOTO L2
   L1
   FRAME SAME
    ICONST_0
   L2
   FRAME SAME1 I
    PUTSTATIC org/mpisws/concurrent/programs/simple/counter/SimpleCounter.$assertionsDisabled : Z
    RETURN
    MAXSTACK = 1
    MAXLOCALS = 0
}
